{"wsj_2305": {"sentences": [{"parsetree": "( (NP (. .)))", "dependencies": [["root", "ROOT-0", ".-1"]], "words": [[".", {"PartOfSpeech": ".", "CharacterOffsetBegin": 0, "CharacterOffsetEnd": 1}]]}, {"parsetree": "( (S (NP (NNP START) (NNP The) (NNP Treasury)) (VP (VBZ plans) (S (VP (TO to) (VP (VP (VB raise) (NP (NP (QP ($ $) (CD 175) (CD million))) (PP (IN in) (NP (JJ new) (NN cash)))) (NP-TMP (NNP Thursday)) (PP (IN by) (S (VP (VBG selling) (NP (NP (QP (RB about) ($ $) (CD 9.75) (CD billion))) (PP (IN of) (NP (JJ 52-week) (NNS bills)))))))) (CC and) (VP (JJ redeeming) (NP (NP (QP ($ $) (CD 9.58) (CD billion))) (PP (IN of) (NP (VBG maturing) (NNS bills))))))))) (. .)))", "dependencies": [["root", "ROOT-0", "plans-4"], ["compound", "Treasury-3", "START-1"], ["compound", "Treasury-3", "The-2"], ["nsubj", "plans-4", "Treasury-3"], ["mark", "raise-6", "to-5"], ["xcomp", "plans-4", "raise-6"], ["dobj", "raise-6", "$-7"], ["compound", "million-9", "175-8"], ["nummod", "$-7", "million-9"], ["case", "cash-12", "in-10"], ["amod", "cash-12", "new-11"], ["nmod", "$-7", "cash-12"], ["nmod:tmod", "raise-6", "Thursday-13"], ["mark", "selling-15", "by-14"], ["advcl", "raise-6", "selling-15"], ["advmod", "$-17", "about-16"], ["dobj", "selling-15", "$-17"], ["compound", "billion-19", "9.75-18"], ["nummod", "$-17", "billion-19"], ["case", "bills-22", "of-20"], ["amod", "bills-22", "52-week-21"], ["nmod", "$-17", "bills-22"], ["cc", "raise-6", "and-23"], ["conj", "raise-6", "redeeming-24"], ["dobj", "redeeming-24", "$-25"], ["compound", "billion-27", "9.58-26"], ["nummod", "$-25", "billion-27"], ["case", "bills-30", "of-28"], ["amod", "bills-30", "maturing-29"], ["nmod", "$-25", "bills-30"], ["punct", "plans-4", ".-31"]], "words": [["START", {"PartOfSpeech": "NNP", "CharacterOffsetBegin": 1, "CharacterOffsetEnd": 6}], ["The", {"PartOfSpeech": "NNP", "CharacterOffsetBegin": 9, "CharacterOffsetEnd": 12}], ["Treasury", {"PartOfSpeech": "NNP", "CharacterOffsetBegin": 13, "CharacterOffsetEnd": 21}], ["plans", {"PartOfSpeech": "VBZ", "CharacterOffsetBegin": 22, "CharacterOffsetEnd": 27}], ["to", {"PartOfSpeech": "TO", "CharacterOffsetBegin": 28, "CharacterOffsetEnd": 30}], ["raise", {"PartOfSpeech": "VB", "CharacterOffsetBegin": 31, "CharacterOffsetEnd": 36}], ["$", {"PartOfSpeech": "$", "CharacterOffsetBegin": 37, "CharacterOffsetEnd": 38}], ["175", {"PartOfSpeech": "CD", "CharacterOffsetBegin": 38, "CharacterOffsetEnd": 41}], ["million", {"PartOfSpeech": "CD", "CharacterOffsetBegin": 42, "CharacterOffsetEnd": 49}], ["in", {"PartOfSpeech": "IN", "CharacterOffsetBegin": 50, "CharacterOffsetEnd": 52}], ["new", {"PartOfSpeech": "JJ", "CharacterOffsetBegin": 53, "CharacterOffsetEnd": 56}], ["cash", {"PartOfSpeech": "NN", "CharacterOffsetBegin": 57, "CharacterOffsetEnd": 61}], ["Thursday", {"PartOfSpeech": "NNP", "CharacterOffsetBegin": 62, "CharacterOffsetEnd": 70}], ["by", {"PartOfSpeech": "IN", "CharacterOffsetBegin": 71, "CharacterOffsetEnd": 73}], ["selling", {"PartOfSpeech": "VBG", "CharacterOffsetBegin": 74, "CharacterOffsetEnd": 81}], ["about", {"PartOfSpeech": "RB", "CharacterOffsetBegin": 82, "CharacterOffsetEnd": 87}], ["$", {"PartOfSpeech": "$", "CharacterOffsetBegin": 88, "CharacterOffsetEnd": 89}], ["9.75", {"PartOfSpeech": "CD", "CharacterOffsetBegin": 89, "CharacterOffsetEnd": 93}], ["billion", {"PartOfSpeech": "CD", "CharacterOffsetBegin": 94, "CharacterOffsetEnd": 101}], ["of", {"PartOfSpeech": "IN", "CharacterOffsetBegin": 102, "CharacterOffsetEnd": 104}], ["52-week", {"PartOfSpeech": "JJ", "CharacterOffsetBegin": 105, "CharacterOffsetEnd": 112}], ["bills", {"PartOfSpeech": "NNS", "CharacterOffsetBegin": 113, "CharacterOffsetEnd": 118}], ["and", {"PartOfSpeech": "CC", "CharacterOffsetBegin": 119, "CharacterOffsetEnd": 122}], ["redeeming", {"PartOfSpeech": "JJ", "CharacterOffsetBegin": 123, "CharacterOffsetEnd": 132}], ["$", {"PartOfSpeech": "$", "CharacterOffsetBegin": 133, "CharacterOffsetEnd": 134}], ["9.58", {"PartOfSpeech": "CD", "CharacterOffsetBegin": 134, "CharacterOffsetEnd": 138}], ["billion", {"PartOfSpeech": "CD", "CharacterOffsetBegin": 139, "CharacterOffsetEnd": 146}], ["of", {"PartOfSpeech": "IN", "CharacterOffsetBegin": 147, "CharacterOffsetEnd": 149}], ["maturing", {"PartOfSpeech": "VBG", "CharacterOffsetBegin": 150, "CharacterOffsetEnd": 158}], ["bills", {"PartOfSpeech": "NNS", "CharacterOffsetBegin": 159, "CharacterOffsetEnd": 164}], [".", {"PartOfSpeech": ".", "CharacterOffsetBegin": 164, "CharacterOffsetEnd": 165}]]}, {"parsetree": "( (S (NP (DT The) (NNS bills)) (VP (VP (MD will) (VP (VB be) (VP (VBN dated) (NP-TMP (NNP Oct.) (CD 26))))) (CC and) (VP (MD will) (VP (VB mature) (NP-TMP (NNP Oct.) (CD 25) (, ,) (CD 1990))))) (. .)))", "dependencies": [["root", "ROOT-0", "dated-5"], ["det", "bills-2", "The-1"], ["nsubjpass", "dated-5", "bills-2"], ["aux", "dated-5", "will-3"], ["auxpass", "dated-5", "be-4"], ["nmod:tmod", "dated-5", "Oct.-6"], ["nummod", "Oct.-6", "26-7"], ["cc", "dated-5", "and-8"], ["aux", "mature-10", "will-9"], ["conj", "dated-5", "mature-10"], ["nmod:tmod", "mature-10", "Oct.-11"], ["nummod", "Oct.-11", "25-12"], ["punct", "Oct.-11", ",-13"], ["nummod", "Oct.-11", "1990-14"], ["punct", "dated-5", ".-15"]], "words": [["The", {"PartOfSpeech": "DT", "CharacterOffsetBegin": 168, "CharacterOffsetEnd": 171}], ["bills", {"PartOfSpeech": "NNS", "CharacterOffsetBegin": 172, "CharacterOffsetEnd": 177}], ["will", {"PartOfSpeech": "MD", "CharacterOffsetBegin": 178, "CharacterOffsetEnd": 182}], ["be", {"PartOfSpeech": "VB", "CharacterOffsetBegin": 183, "CharacterOffsetEnd": 185}], ["dated", {"PartOfSpeech": "VBN", "CharacterOffsetBegin": 186, "CharacterOffsetEnd": 191}], ["Oct.", {"PartOfSpeech": "NNP", "CharacterOffsetBegin": 192, "CharacterOffsetEnd": 196}], ["26", {"PartOfSpeech": "CD", "CharacterOffsetBegin": 197, "CharacterOffsetEnd": 199}], ["and", {"PartOfSpeech": "CC", "CharacterOffsetBegin": 200, "CharacterOffsetEnd": 203}], ["will", {"PartOfSpeech": "MD", "CharacterOffsetBegin": 204, "CharacterOffsetEnd": 208}], ["mature", {"PartOfSpeech": "VB", "CharacterOffsetBegin": 209, "CharacterOffsetEnd": 215}], ["Oct.", {"PartOfSpeech": "NNP", "CharacterOffsetBegin": 216, "CharacterOffsetEnd": 220}], ["25", {"PartOfSpeech": "CD", "CharacterOffsetBegin": 221, "CharacterOffsetEnd": 223}], [",", {"PartOfSpeech": ",", "CharacterOffsetBegin": 223, "CharacterOffsetEnd": 224}], ["1990", {"PartOfSpeech": "CD", "CharacterOffsetBegin": 225, "CharacterOffsetEnd": 229}], [".", {"PartOfSpeech": ".", "CharacterOffsetBegin": 229, "CharacterOffsetEnd": 230}]]}, {"parsetree": "( (S (NP (PRP They)) (VP (MD will) (VP (VB be) (ADJP (JJ available) (PP (IN in) (NP (NP (JJ minimum) (NNS denominations)) (PP (IN of) (NP ($ $) (CD 10,000)))))))) (. .)))", "dependencies": [["root", "ROOT-0", "available-4"], ["nsubj", "available-4", "They-1"], ["aux", "available-4", "will-2"], ["cop", "available-4", "be-3"], ["case", "denominations-7", "in-5"], ["amod", "denominations-7", "minimum-6"], ["nmod", "available-4", "denominations-7"], ["case", "10,000-10", "of-8"], ["dep", "10,000-10", "$-9"], ["nmod", "denominations-7", "10,000-10"], ["punct", "available-4", ".-11"]], "words": [["They", {"PartOfSpeech": "PRP", "CharacterOffsetBegin": 231, "CharacterOffsetEnd": 235}], ["will", {"PartOfSpeech": "MD", "CharacterOffsetBegin": 236, "CharacterOffsetEnd": 240}], ["be", {"PartOfSpeech": "VB", "CharacterOffsetBegin": 241, "CharacterOffsetEnd": 243}], ["available", {"PartOfSpeech": "JJ", "CharacterOffsetBegin": 244, "CharacterOffsetEnd": 253}], ["in", {"PartOfSpeech": "IN", "CharacterOffsetBegin": 254, "CharacterOffsetEnd": 256}], ["minimum", {"PartOfSpeech": "JJ", "CharacterOffsetBegin": 257, "CharacterOffsetEnd": 264}], ["denominations", {"PartOfSpeech": "NNS", "CharacterOffsetBegin": 265, "CharacterOffsetEnd": 278}], ["of", {"PartOfSpeech": "IN", "CharacterOffsetBegin": 279, "CharacterOffsetEnd": 281}], ["$", {"PartOfSpeech": "$", "CharacterOffsetBegin": 282, "CharacterOffsetEnd": 283}], ["10,000", {"PartOfSpeech": "CD", "CharacterOffsetBegin": 283, "CharacterOffsetEnd": 289}], [".", {"PartOfSpeech": ".", "CharacterOffsetBegin": 289, "CharacterOffsetEnd": 290}]]}, {"parsetree": "( (S (NP (NNS Bids)) (VP (MD must) (VP (VB be) (VP (VBN received) (PP (IN by) (NP (CD 1) (RB p.m.) (NNP EDT))) (NP-TMP (NNP Thursday)) (PP (PP (IN at) (NP (DT the) (NNP Treasury))) (CC or) (PP (IN at) (NP (NNP Federal) (NNP Reserve) (NNS banks) (CC or) (NNS branches))))))) (. .)))", "dependencies": [["root", "ROOT-0", "received-4"], ["nsubjpass", "received-4", "Bids-1"], ["aux", "received-4", "must-2"], ["auxpass", "received-4", "be-3"], ["case", "EDT-8", "by-5"], ["nummod", "EDT-8", "1-6"], ["advmod", "EDT-8", "p.m.-7"], ["nmod", "received-4", "EDT-8"], ["nmod:tmod", "received-4", "Thursday-9"], ["case", "Treasury-12", "at-10"], ["det", "Treasury-12", "the-11"], ["nmod", "received-4", "Treasury-12"], ["cc", "Treasury-12", "or-13"], ["case", "banks-17", "at-14"], ["compound", "banks-17", "Federal-15"], ["compound", "banks-17", "Reserve-16"], ["conj", "Treasury-12", "banks-17"], ["cc", "banks-17", "or-18"], ["conj", "banks-17", "branches-19"], ["punct", "received-4", ".-20"]], "words": [["Bids", {"PartOfSpeech": "NNS", "CharacterOffsetBegin": 293, "CharacterOffsetEnd": 297}], ["must", {"PartOfSpeech": "MD", "CharacterOffsetBegin": 298, "CharacterOffsetEnd": 302}], ["be", {"PartOfSpeech": "VB", "CharacterOffsetBegin": 303, "CharacterOffsetEnd": 305}], ["received", {"PartOfSpeech": "VBN", "CharacterOffsetBegin": 306, "CharacterOffsetEnd": 314}], ["by", {"PartOfSpeech": "IN", "CharacterOffsetBegin": 315, "CharacterOffsetEnd": 317}], ["1", {"PartOfSpeech": "CD", "CharacterOffsetBegin": 318, "CharacterOffsetEnd": 319}], ["p.m.", {"PartOfSpeech": "RB", "CharacterOffsetBegin": 320, "CharacterOffsetEnd": 324}], ["EDT", {"PartOfSpeech": "NNP", "CharacterOffsetBegin": 325, "CharacterOffsetEnd": 328}], ["Thursday", {"PartOfSpeech": "NNP", "CharacterOffsetBegin": 329, "CharacterOffsetEnd": 337}], ["at", {"PartOfSpeech": "IN", "CharacterOffsetBegin": 338, "CharacterOffsetEnd": 340}], ["the", {"PartOfSpeech": "DT", "CharacterOffsetBegin": 341, "CharacterOffsetEnd": 344}], ["Treasury", {"PartOfSpeech": "NNP", "CharacterOffsetBegin": 345, "CharacterOffsetEnd": 353}], ["or", {"PartOfSpeech": "CC", "CharacterOffsetBegin": 354, "CharacterOffsetEnd": 356}], ["at", {"PartOfSpeech": "IN", "CharacterOffsetBegin": 357, "CharacterOffsetEnd": 359}], ["Federal", {"PartOfSpeech": "NNP", "CharacterOffsetBegin": 360, "CharacterOffsetEnd": 367}], ["Reserve", {"PartOfSpeech": "NNP", "CharacterOffsetBegin": 368, "CharacterOffsetEnd": 375}], ["banks", {"PartOfSpeech": "NNS", "CharacterOffsetBegin": 376, "CharacterOffsetEnd": 381}], ["or", {"PartOfSpeech": "CC", "CharacterOffsetBegin": 382, "CharacterOffsetEnd": 384}], ["branches", {"PartOfSpeech": "NNS", "CharacterOffsetBegin": 385, "CharacterOffsetEnd": 393}], [".", {"PartOfSpeech": ".", "CharacterOffsetBegin": 393, "CharacterOffsetEnd": 394}]]}]}}