{"wsj_2339": {"sentences": [{"parsetree": "( (NP (. .)))", "dependencies": [["root", "ROOT-0", ".-1"]], "words": [[".", {"PartOfSpeech": ".", "CharacterOffsetBegin": 0, "CharacterOffsetEnd": 1}]]}, {"parsetree": "( (S (NP (NP (NNP START) (NNP Institut) (NNP Merieux) (NNP S.A.)) (PP (IN of) (NP (NNP France)))) (VP (VBD said) (SBAR (S (NP (DT the) (JJ Canadian) (NN government)) (VP (VBD raised) (NP (DT an) (NN obstacle)) (PP (TO to) (NP (NP (PRP$ its) (JJ proposed) (NN acquisition)) (PP (IN of) (NP (NP (NNP Connaught) (NNP BioSciences) (NNP Inc.)) (PP (IN for) (NP (NP (QP (CD 942) (CD million)) (JJ Canadian) (NNS dollars)) (PRN (-LRB- -LRB-) (NP (QP ($ US$) (CD 801.6) (CD million))) (-RRB- -RRB-)))))))))))) (. .)))", "dependencies": [["root", "ROOT-0", "said-7"], ["compound", "S.A.-4", "START-1"], ["compound", "S.A.-4", "Institut-2"], ["compound", "S.A.-4", "Merieux-3"], ["nsubj", "said-7", "S.A.-4"], ["case", "France-6", "of-5"], ["nmod", "S.A.-4", "France-6"], ["det", "government-10", "the-8"], ["amod", "government-10", "Canadian-9"], ["nsubj", "raised-11", "government-10"], ["ccomp", "said-7", "raised-11"], ["det", "obstacle-13", "an-12"], ["dobj", "raised-11", "obstacle-13"], ["case", "acquisition-17", "to-14"], ["nmod:poss", "acquisition-17", "its-15"], ["amod", "acquisition-17", "proposed-16"], ["nmod", "raised-11", "acquisition-17"], ["case", "Inc.-21", "of-18"], ["compound", "Inc.-21", "Connaught-19"], ["compound", "Inc.-21", "BioSciences-20"], ["nmod", "acquisition-17", "Inc.-21"], ["case", "dollars-26", "for-22"], ["compound", "million-24", "942-23"], ["nummod", "dollars-26", "million-24"], ["amod", "dollars-26", "Canadian-25"], ["nmod", "Inc.-21", "dollars-26"], ["punct", "US$-28", "-LRB--27"], ["dep", "dollars-26", "US$-28"], ["compound", "million-30", "801.6-29"], ["nummod", "US$-28", "million-30"], ["punct", "US$-28", "-RRB--31"], ["punct", "said-7", ".-32"]], "words": [["START", {"PartOfSpeech": "NNP", "CharacterOffsetBegin": 1, "CharacterOffsetEnd": 6}], ["Institut", {"PartOfSpeech": "NNP", "CharacterOffsetBegin": 9, "CharacterOffsetEnd": 17}], ["Merieux", {"PartOfSpeech": "NNP", "CharacterOffsetBegin": 18, "CharacterOffsetEnd": 25}], ["S.A.", {"PartOfSpeech": "NNP", "CharacterOffsetBegin": 26, "CharacterOffsetEnd": 30}], ["of", {"PartOfSpeech": "IN", "CharacterOffsetBegin": 31, "CharacterOffsetEnd": 33}], ["France", {"PartOfSpeech": "NNP", "CharacterOffsetBegin": 34, "CharacterOffsetEnd": 40}], ["said", {"PartOfSpeech": "VBD", "CharacterOffsetBegin": 41, "CharacterOffsetEnd": 45}], ["the", {"PartOfSpeech": "DT", "CharacterOffsetBegin": 46, "CharacterOffsetEnd": 49}], ["Canadian", {"PartOfSpeech": "JJ", "CharacterOffsetBegin": 50, "CharacterOffsetEnd": 58}], ["government", {"PartOfSpeech": "NN", "CharacterOffsetBegin": 59, "CharacterOffsetEnd": 69}], ["raised", {"PartOfSpeech": "VBD", "CharacterOffsetBegin": 70, "CharacterOffsetEnd": 76}], ["an", {"PartOfSpeech": "DT", "CharacterOffsetBegin": 77, "CharacterOffsetEnd": 79}], ["obstacle", {"PartOfSpeech": "NN", "CharacterOffsetBegin": 80, "CharacterOffsetEnd": 88}], ["to", {"PartOfSpeech": "TO", "CharacterOffsetBegin": 89, "CharacterOffsetEnd": 91}], ["its", {"PartOfSpeech": "PRP$", "CharacterOffsetBegin": 92, "CharacterOffsetEnd": 95}], ["proposed", {"PartOfSpeech": "JJ", "CharacterOffsetBegin": 96, "CharacterOffsetEnd": 104}], ["acquisition", {"PartOfSpeech": "NN", "CharacterOffsetBegin": 105, "CharacterOffsetEnd": 116}], ["of", {"PartOfSpeech": "IN", "CharacterOffsetBegin": 117, "CharacterOffsetEnd": 119}], ["Connaught", {"PartOfSpeech": "NNP", "CharacterOffsetBegin": 120, "CharacterOffsetEnd": 129}], ["BioSciences", {"PartOfSpeech": "NNP", "CharacterOffsetBegin": 130, "CharacterOffsetEnd": 141}], ["Inc.", {"PartOfSpeech": "NNP", "CharacterOffsetBegin": 142, "CharacterOffsetEnd": 146}], ["for", {"PartOfSpeech": "IN", "CharacterOffsetBegin": 147, "CharacterOffsetEnd": 150}], ["942", {"PartOfSpeech": "CD", "CharacterOffsetBegin": 151, "CharacterOffsetEnd": 154}], ["million", {"PartOfSpeech": "CD", "CharacterOffsetBegin": 155, "CharacterOffsetEnd": 162}], ["Canadian", {"PartOfSpeech": "JJ", "CharacterOffsetBegin": 163, "CharacterOffsetEnd": 171}], ["dollars", {"PartOfSpeech": "NNS", "CharacterOffsetBegin": 172, "CharacterOffsetEnd": 179}], ["-LRB-", {"PartOfSpeech": "-LRB-", "CharacterOffsetBegin": 180, "CharacterOffsetEnd": 181}], ["US$", {"PartOfSpeech": "$", "CharacterOffsetBegin": 181, "CharacterOffsetEnd": 184}], ["801.6", {"PartOfSpeech": "CD", "CharacterOffsetBegin": 184, "CharacterOffsetEnd": 189}], ["million", {"PartOfSpeech": "CD", "CharacterOffsetBegin": 190, "CharacterOffsetEnd": 197}], ["-RRB-", {"PartOfSpeech": "-RRB-", "CharacterOffsetBegin": 197, "CharacterOffsetEnd": 198}], [".", {"PartOfSpeech": ".", "CharacterOffsetBegin": 198, "CharacterOffsetEnd": 199}]]}, {"parsetree": "( (S (NP (NNP Merieux)) (VP (VBD said) (SBAR (S (NP (NP (NP (DT the) (NN government) (POS 's)) (NN minister)) (PP (IN of) (NP (NN industry) (, ,) (NN science) (CC and) (NN technology)))) (VP (VBD told) (NP (PRP it)) (SBAR (IN that) (S (NP (PRP he)) (VP (VBD was) (RB n't) (ADJP (VBN convinced) (SBAR (IN that) (S (NP (DT the) (NN purchase)) (VP (VBZ is) (ADJP (JJ likely) (S (VP (TO to) (VP (VB be) (PP (IN of) (`` ``) (NP (JJ net) (NN benefit)) ('' '')) (PP (TO to) (NP (NNP Canada)))))))))))))))))) (. .)))", "dependencies": [["root", "ROOT-0", "said-2"], ["nsubj", "said-2", "Merieux-1"], ["det", "government-4", "the-3"], ["nmod:poss", "minister-6", "government-4"], ["case", "government-4", "'s-5"], ["nsubj", "told-13", "minister-6"], ["case", "industry-8", "of-7"], ["nmod", "minister-6", "industry-8"], ["punct", "industry-8", ",-9"], ["conj", "industry-8", "science-10"], ["cc", "industry-8", "and-11"], ["conj", "industry-8", "technology-12"], ["ccomp", "said-2", "told-13"], ["dobj", "told-13", "it-14"], ["mark", "convinced-19", "that-15"], ["nsubjpass", "convinced-19", "he-16"], ["auxpass", "convinced-19", "was-17"], ["neg", "convinced-19", "n't-18"], ["ccomp", "told-13", "convinced-19"], ["mark", "likely-24", "that-20"], ["det", "purchase-22", "the-21"], ["nsubj", "likely-24", "purchase-22"], ["cop", "likely-24", "is-23"], ["ccomp", "convinced-19", "likely-24"], ["mark", "benefit-30", "to-25"], ["cop", "benefit-30", "be-26"], ["case", "benefit-30", "of-27"], ["punct", "benefit-30", "``-28"], ["amod", "benefit-30", "net-29"], ["xcomp", "likely-24", "benefit-30"], ["punct", "benefit-30", "''-31"], ["case", "Canada-33", "to-32"], ["nmod", "benefit-30", "Canada-33"], ["punct", "said-2", ".-34"]], "words": [["Merieux", {"PartOfSpeech": "NNP", "CharacterOffsetBegin": 202, "CharacterOffsetEnd": 209}], ["said", {"PartOfSpeech": "VBD", "CharacterOffsetBegin": 210, "CharacterOffsetEnd": 214}], ["the", {"PartOfSpeech": "DT", "CharacterOffsetBegin": 215, "CharacterOffsetEnd": 218}], ["government", {"PartOfSpeech": "NN", "CharacterOffsetBegin": 219, "CharacterOffsetEnd": 229}], ["'s", {"PartOfSpeech": "POS", "CharacterOffsetBegin": 229, "CharacterOffsetEnd": 231}], ["minister", {"PartOfSpeech": "NN", "CharacterOffsetBegin": 232, "CharacterOffsetEnd": 240}], ["of", {"PartOfSpeech": "IN", "CharacterOffsetBegin": 241, "CharacterOffsetEnd": 243}], ["industry", {"PartOfSpeech": "NN", "CharacterOffsetBegin": 244, "CharacterOffsetEnd": 252}], [",", {"PartOfSpeech": ",", "CharacterOffsetBegin": 252, "CharacterOffsetEnd": 253}], ["science", {"PartOfSpeech": "NN", "CharacterOffsetBegin": 254, "CharacterOffsetEnd": 261}], ["and", {"PartOfSpeech": "CC", "CharacterOffsetBegin": 262, "CharacterOffsetEnd": 265}], ["technology", {"PartOfSpeech": "NN", "CharacterOffsetBegin": 266, "CharacterOffsetEnd": 276}], ["told", {"PartOfSpeech": "VBD", "CharacterOffsetBegin": 277, "CharacterOffsetEnd": 281}], ["it", {"PartOfSpeech": "PRP", "CharacterOffsetBegin": 282, "CharacterOffsetEnd": 284}], ["that", {"PartOfSpeech": "IN", "CharacterOffsetBegin": 285, "CharacterOffsetEnd": 289}], ["he", {"PartOfSpeech": "PRP", "CharacterOffsetBegin": 290, "CharacterOffsetEnd": 292}], ["was", {"PartOfSpeech": "VBD", "CharacterOffsetBegin": 293, "CharacterOffsetEnd": 296}], ["n't", {"PartOfSpeech": "RB", "CharacterOffsetBegin": 296, "CharacterOffsetEnd": 299}], ["convinced", {"PartOfSpeech": "VBN", "CharacterOffsetBegin": 300, "CharacterOffsetEnd": 309}], ["that", {"PartOfSpeech": "IN", "CharacterOffsetBegin": 310, "CharacterOffsetEnd": 314}], ["the", {"PartOfSpeech": "DT", "CharacterOffsetBegin": 315, "CharacterOffsetEnd": 318}], ["purchase", {"PartOfSpeech": "NN", "CharacterOffsetBegin": 319, "CharacterOffsetEnd": 327}], ["is", {"PartOfSpeech": "VBZ", "CharacterOffsetBegin": 328, "CharacterOffsetEnd": 330}], ["likely", {"PartOfSpeech": "JJ", "CharacterOffsetBegin": 331, "CharacterOffsetEnd": 337}], ["to", {"PartOfSpeech": "TO", "CharacterOffsetBegin": 338, "CharacterOffsetEnd": 340}], ["be", {"PartOfSpeech": "VB", "CharacterOffsetBegin": 341, "CharacterOffsetEnd": 343}], ["of", {"PartOfSpeech": "IN", "CharacterOffsetBegin": 344, "CharacterOffsetEnd": 346}], ["``", {"PartOfSpeech": "``", "CharacterOffsetBegin": 347, "CharacterOffsetEnd": 348}], ["net", {"PartOfSpeech": "JJ", "CharacterOffsetBegin": 348, "CharacterOffsetEnd": 351}], ["benefit", {"PartOfSpeech": "NN", "CharacterOffsetBegin": 352, "CharacterOffsetEnd": 359}], ["''", {"PartOfSpeech": "''", "CharacterOffsetBegin": 359, "CharacterOffsetEnd": 360}], ["to", {"PartOfSpeech": "TO", "CharacterOffsetBegin": 361, "CharacterOffsetEnd": 363}], ["Canada", {"PartOfSpeech": "NNP", "CharacterOffsetBegin": 364, "CharacterOffsetEnd": 370}], [".", {"PartOfSpeech": ".", "CharacterOffsetBegin": 370, "CharacterOffsetEnd": 371}]]}, {"parsetree": "( (S (NP (JJ Canadian) (NN investment) (NNS rules)) (VP (VBP require) (SBAR (IN that) (S (NP (JJ big) (JJ foreign) (NNS takeovers)) (VP (VBP meet) (PP (IN that) (NP (NN standard))))))) (. .)))", "dependencies": [["root", "ROOT-0", "require-4"], ["amod", "rules-3", "Canadian-1"], ["compound", "rules-3", "investment-2"], ["nsubj", "require-4", "rules-3"], ["mark", "meet-9", "that-5"], ["amod", "takeovers-8", "big-6"], ["amod", "takeovers-8", "foreign-7"], ["nsubj", "meet-9", "takeovers-8"], ["ccomp", "require-4", "meet-9"], ["case", "standard-11", "that-10"], ["nmod", "meet-9", "standard-11"], ["punct", "require-4", ".-12"]], "words": [["Canadian", {"PartOfSpeech": "JJ", "CharacterOffsetBegin": 372, "CharacterOffsetEnd": 380}], ["investment", {"PartOfSpeech": "NN", "CharacterOffsetBegin": 381, "CharacterOffsetEnd": 391}], ["rules", {"PartOfSpeech": "NNS", "CharacterOffsetBegin": 392, "CharacterOffsetEnd": 397}], ["require", {"PartOfSpeech": "VBP", "CharacterOffsetBegin": 398, "CharacterOffsetEnd": 405}], ["that", {"PartOfSpeech": "IN", "CharacterOffsetBegin": 406, "CharacterOffsetEnd": 410}], ["big", {"PartOfSpeech": "JJ", "CharacterOffsetBegin": 411, "CharacterOffsetEnd": 414}], ["foreign", {"PartOfSpeech": "JJ", "CharacterOffsetBegin": 415, "CharacterOffsetEnd": 422}], ["takeovers", {"PartOfSpeech": "NNS", "CharacterOffsetBegin": 423, "CharacterOffsetEnd": 432}], ["meet", {"PartOfSpeech": "VBP", "CharacterOffsetBegin": 433, "CharacterOffsetEnd": 437}], ["that", {"PartOfSpeech": "IN", "CharacterOffsetBegin": 438, "CharacterOffsetEnd": 442}], ["standard", {"PartOfSpeech": "NN", "CharacterOffsetBegin": 443, "CharacterOffsetEnd": 451}], [".", {"PartOfSpeech": ".", "CharacterOffsetBegin": 451, "CharacterOffsetEnd": 452}]]}, {"parsetree": "( (S (NP (DT The) (JJ French) (NN company)) (VP (VBD said) (SBAR (S (NP (DT the) (NN government)) (VP (VBD gave) (NP (PRP it)) (NP (CD 30) (NNS days)) (PP (IN in) (SBAR (WHNP (WDT which)) (S (VP (TO to) (VP (VB submit) (NP (NN information)) (PP (TO to) (NP (NP (JJ further) (NN support)) (NP (PRP$ its) (NN takeover) (NN plan))))))))))))) (. .)))", "dependencies": [["root", "ROOT-0", "said-4"], ["det", "company-3", "The-1"], ["amod", "company-3", "French-2"], ["nsubj", "said-4", "company-3"], ["det", "government-6", "the-5"], ["nsubj", "gave-7", "government-6"], ["ccomp", "said-4", "gave-7"], ["dobj", "gave-7", "it-8"], ["nummod", "days-10", "30-9"], ["nmod:tmod", "gave-7", "days-10"], ["mark", "submit-14", "in-11"], ["nsubj", "submit-14", "which-12"], ["mark", "submit-14", "to-13"], ["advcl", "gave-7", "submit-14"], ["dobj", "submit-14", "information-15"], ["case", "support-18", "to-16"], ["amod", "support-18", "further-17"], ["nmod", "submit-14", "support-18"], ["nmod:poss", "plan-21", "its-19"], ["compound", "plan-21", "takeover-20"], ["dep", "support-18", "plan-21"], ["punct", "said-4", ".-22"]], "words": [["The", {"PartOfSpeech": "DT", "CharacterOffsetBegin": 455, "CharacterOffsetEnd": 458}], ["French", {"PartOfSpeech": "JJ", "CharacterOffsetBegin": 459, "CharacterOffsetEnd": 465}], ["company", {"PartOfSpeech": "NN", "CharacterOffsetBegin": 466, "CharacterOffsetEnd": 473}], ["said", {"PartOfSpeech": "VBD", "CharacterOffsetBegin": 474, "CharacterOffsetEnd": 478}], ["the", {"PartOfSpeech": "DT", "CharacterOffsetBegin": 479, "CharacterOffsetEnd": 482}], ["government", {"PartOfSpeech": "NN", "CharacterOffsetBegin": 483, "CharacterOffsetEnd": 493}], ["gave", {"PartOfSpeech": "VBD", "CharacterOffsetBegin": 494, "CharacterOffsetEnd": 498}], ["it", {"PartOfSpeech": "PRP", "CharacterOffsetBegin": 499, "CharacterOffsetEnd": 501}], ["30", {"PartOfSpeech": "CD", "CharacterOffsetBegin": 502, "CharacterOffsetEnd": 504}], ["days", {"PartOfSpeech": "NNS", "CharacterOffsetBegin": 505, "CharacterOffsetEnd": 509}], ["in", {"PartOfSpeech": "IN", "CharacterOffsetBegin": 510, "CharacterOffsetEnd": 512}], ["which", {"PartOfSpeech": "WDT", "CharacterOffsetBegin": 513, "CharacterOffsetEnd": 518}], ["to", {"PartOfSpeech": "TO", "CharacterOffsetBegin": 519, "CharacterOffsetEnd": 521}], ["submit", {"PartOfSpeech": "VB", "CharacterOffsetBegin": 522, "CharacterOffsetEnd": 528}], ["information", {"PartOfSpeech": "NN", "CharacterOffsetBegin": 529, "CharacterOffsetEnd": 540}], ["to", {"PartOfSpeech": "TO", "CharacterOffsetBegin": 541, "CharacterOffsetEnd": 543}], ["further", {"PartOfSpeech": "JJ", "CharacterOffsetBegin": 544, "CharacterOffsetEnd": 551}], ["support", {"PartOfSpeech": "NN", "CharacterOffsetBegin": 552, "CharacterOffsetEnd": 559}], ["its", {"PartOfSpeech": "PRP$", "CharacterOffsetBegin": 560, "CharacterOffsetEnd": 563}], ["takeover", {"PartOfSpeech": "NN", "CharacterOffsetBegin": 564, "CharacterOffsetEnd": 572}], ["plan", {"PartOfSpeech": "NN", "CharacterOffsetBegin": 573, "CharacterOffsetEnd": 577}], [".", {"PartOfSpeech": ".", "CharacterOffsetBegin": 577, "CharacterOffsetEnd": 578}]]}, {"parsetree": "( (S (NP (DT Both) (NNP Merieux) (CC and) (NNP Connaught)) (VP (VBP are) (NP (NN biotechnology) (NN research) (CC and) (NN vaccine) (NN manufacturing) (NNS concerns))) (. .)))", "dependencies": [["root", "ROOT-0", "research-7"], ["cc:preconj", "Merieux-2", "Both-1"], ["nsubj", "research-7", "Merieux-2"], ["cc", "Merieux-2", "and-3"], ["conj", "Merieux-2", "Connaught-4"], ["cop", "research-7", "are-5"], ["compound", "research-7", "biotechnology-6"], ["cc", "research-7", "and-8"], ["compound", "concerns-11", "vaccine-9"], ["compound", "concerns-11", "manufacturing-10"], ["conj", "research-7", "concerns-11"], ["punct", "research-7", ".-12"]], "words": [["Both", {"PartOfSpeech": "DT", "CharacterOffsetBegin": 581, "CharacterOffsetEnd": 585}], ["Merieux", {"PartOfSpeech": "NNP", "CharacterOffsetBegin": 586, "CharacterOffsetEnd": 593}], ["and", {"PartOfSpeech": "CC", "CharacterOffsetBegin": 594, "CharacterOffsetEnd": 597}], ["Connaught", {"PartOfSpeech": "NNP", "CharacterOffsetBegin": 598, "CharacterOffsetEnd": 607}], ["are", {"PartOfSpeech": "VBP", "CharacterOffsetBegin": 608, "CharacterOffsetEnd": 611}], ["biotechnology", {"PartOfSpeech": "NN", "CharacterOffsetBegin": 612, "CharacterOffsetEnd": 625}], ["research", {"PartOfSpeech": "NN", "CharacterOffsetBegin": 626, "CharacterOffsetEnd": 634}], ["and", {"PartOfSpeech": "CC", "CharacterOffsetBegin": 635, "CharacterOffsetEnd": 638}], ["vaccine", {"PartOfSpeech": "NN", "CharacterOffsetBegin": 639, "CharacterOffsetEnd": 646}], ["manufacturing", {"PartOfSpeech": "NN", "CharacterOffsetBegin": 647, "CharacterOffsetEnd": 660}], ["concerns", {"PartOfSpeech": "NNS", "CharacterOffsetBegin": 661, "CharacterOffsetEnd": 669}], [".", {"PartOfSpeech": ".", "CharacterOffsetBegin": 669, "CharacterOffsetEnd": 670}]]}, {"parsetree": "( (S (NP (NP (DT The) (NN government) (POS 's)) (NN action)) (VP (VBD was) (ADJP (JJ unusual))) (. .)))", "dependencies": [["root", "ROOT-0", "unusual-6"], ["det", "government-2", "The-1"], ["nmod:poss", "action-4", "government-2"], ["case", "government-2", "'s-3"], ["nsubj", "unusual-6", "action-4"], ["cop", "unusual-6", "was-5"], ["punct", "unusual-6", ".-7"]], "words": [["The", {"PartOfSpeech": "DT", "CharacterOffsetBegin": 673, "CharacterOffsetEnd": 676}], ["government", {"PartOfSpeech": "NN", "CharacterOffsetBegin": 677, "CharacterOffsetEnd": 687}], ["'s", {"PartOfSpeech": "POS", "CharacterOffsetBegin": 687, "CharacterOffsetEnd": 689}], ["action", {"PartOfSpeech": "NN", "CharacterOffsetBegin": 690, "CharacterOffsetEnd": 696}], ["was", {"PartOfSpeech": "VBD", "CharacterOffsetBegin": 697, "CharacterOffsetEnd": 700}], ["unusual", {"PartOfSpeech": "JJ", "CharacterOffsetBegin": 701, "CharacterOffsetEnd": 708}], [".", {"PartOfSpeech": ".", "CharacterOffsetBegin": 708, "CharacterOffsetEnd": 709}]]}, {"parsetree": "( (S (NP (NP (NNP Alan) (NNP Nymark)) (, ,) (NP (NP (JJ executive) (NN vice) (NN president)) (PP (IN of) (NP (NP (NNP Investment) (NNP Canada)) (, ,) (SBAR (WHNP (WDT which)) (S (VP (VBZ oversees) (NP (JJ foreign) (NNS takeovers)))))))) (, ,)) (VP (VBD said) (SBAR (S (NP (PRP it)) (VP (VBD marked) (NP (DT the) (JJ first) (NN time)) (PP (IN in) (NP (PRP$ its) (JJ four-year) (NN history))) (SBAR (IN that) (S (NP (DT the) (NN agency)) (VP (VBZ has) (VP (VBN made) (NP (DT an) (JJ adverse) (JJ net-benefit) (NN decision)) (PP (IN about) (NP (NP (DT the) (NN acquisition)) (PP (IN of) (NP (DT a) (ADJP (RB publicly) (VBN traded)) (NN company))))))))))))) (. .)))", "dependencies": [["root", "ROOT-0", "said-16"], ["compound", "Nymark-2", "Alan-1"], ["nsubj", "said-16", "Nymark-2"], ["punct", "Nymark-2", ",-3"], ["amod", "president-6", "executive-4"], ["compound", "president-6", "vice-5"], ["appos", "Nymark-2", "president-6"], ["case", "Canada-9", "of-7"], ["compound", "Canada-9", "Investment-8"], ["nmod", "president-6", "Canada-9"], ["punct", "Canada-9", ",-10"], ["nsubj", "oversees-12", "which-11"], ["acl:relcl", "Canada-9", "oversees-12"], ["amod", "takeovers-14", "foreign-13"], ["dobj", "oversees-12", "takeovers-14"], ["punct", "Nymark-2", ",-15"], ["nsubj", "marked-18", "it-17"], ["ccomp", "said-16", "marked-18"], ["det", "time-21", "the-19"], ["amod", "time-21", "first-20"], ["dobj", "marked-18", "time-21"], ["case", "history-25", "in-22"], ["nmod:poss", "history-25", "its-23"], ["amod", "history-25", "four-year-24"], ["nmod", "marked-18", "history-25"], ["mark", "made-30", "that-26"], ["det", "agency-28", "the-27"], ["nsubj", "made-30", "agency-28"], ["aux", "made-30", "has-29"], ["ccomp", "marked-18", "made-30"], ["det", "decision-34", "an-31"], ["amod", "decision-34", "adverse-32"], ["amod", "decision-34", "net-benefit-33"], ["dobj", "made-30", "decision-34"], ["case", "acquisition-37", "about-35"], ["det", "acquisition-37", "the-36"], ["nmod", "made-30", "acquisition-37"], ["case", "company-42", "of-38"], ["det", "company-42", "a-39"], ["advmod", "traded-41", "publicly-40"], ["amod", "company-42", "traded-41"], ["nmod", "acquisition-37", "company-42"], ["punct", "said-16", ".-43"]], "words": [["Alan", {"PartOfSpeech": "NNP", "CharacterOffsetBegin": 710, "CharacterOffsetEnd": 714}], ["Nymark", {"PartOfSpeech": "NNP", "CharacterOffsetBegin": 715, "CharacterOffsetEnd": 721}], [",", {"PartOfSpeech": ",", "CharacterOffsetBegin": 721, "CharacterOffsetEnd": 722}], ["executive", {"PartOfSpeech": "JJ", "CharacterOffsetBegin": 723, "CharacterOffsetEnd": 732}], ["vice", {"PartOfSpeech": "NN", "CharacterOffsetBegin": 733, "CharacterOffsetEnd": 737}], ["president", {"PartOfSpeech": "NN", "CharacterOffsetBegin": 738, "CharacterOffsetEnd": 747}], ["of", {"PartOfSpeech": "IN", "CharacterOffsetBegin": 748, "CharacterOffsetEnd": 750}], ["Investment", {"PartOfSpeech": "NNP", "CharacterOffsetBegin": 751, "CharacterOffsetEnd": 761}], ["Canada", {"PartOfSpeech": "NNP", "CharacterOffsetBegin": 762, "CharacterOffsetEnd": 768}], [",", {"PartOfSpeech": ",", "CharacterOffsetBegin": 768, "CharacterOffsetEnd": 769}], ["which", {"PartOfSpeech": "WDT", "CharacterOffsetBegin": 770, "CharacterOffsetEnd": 775}], ["oversees", {"PartOfSpeech": "VBZ", "CharacterOffsetBegin": 776, "CharacterOffsetEnd": 784}], ["foreign", {"PartOfSpeech": "JJ", "CharacterOffsetBegin": 785, "CharacterOffsetEnd": 792}], ["takeovers", {"PartOfSpeech": "NNS", "CharacterOffsetBegin": 793, "CharacterOffsetEnd": 802}], [",", {"PartOfSpeech": ",", "CharacterOffsetBegin": 802, "CharacterOffsetEnd": 803}], ["said", {"PartOfSpeech": "VBD", "CharacterOffsetBegin": 804, "CharacterOffsetEnd": 808}], ["it", {"PartOfSpeech": "PRP", "CharacterOffsetBegin": 809, "CharacterOffsetEnd": 811}], ["marked", {"PartOfSpeech": "VBD", "CharacterOffsetBegin": 812, "CharacterOffsetEnd": 818}], ["the", {"PartOfSpeech": "DT", "CharacterOffsetBegin": 819, "CharacterOffsetEnd": 822}], ["first", {"PartOfSpeech": "JJ", "CharacterOffsetBegin": 823, "CharacterOffsetEnd": 828}], ["time", {"PartOfSpeech": "NN", "CharacterOffsetBegin": 829, "CharacterOffsetEnd": 833}], ["in", {"PartOfSpeech": "IN", "CharacterOffsetBegin": 834, "CharacterOffsetEnd": 836}], ["its", {"PartOfSpeech": "PRP$", "CharacterOffsetBegin": 837, "CharacterOffsetEnd": 840}], ["four-year", {"PartOfSpeech": "JJ", "CharacterOffsetBegin": 841, "CharacterOffsetEnd": 850}], ["history", {"PartOfSpeech": "NN", "CharacterOffsetBegin": 851, "CharacterOffsetEnd": 858}], ["that", {"PartOfSpeech": "IN", "CharacterOffsetBegin": 859, "CharacterOffsetEnd": 863}], ["the", {"PartOfSpeech": "DT", "CharacterOffsetBegin": 864, "CharacterOffsetEnd": 867}], ["agency", {"PartOfSpeech": "NN", "CharacterOffsetBegin": 868, "CharacterOffsetEnd": 874}], ["has", {"PartOfSpeech": "VBZ", "CharacterOffsetBegin": 875, "CharacterOffsetEnd": 878}], ["made", {"PartOfSpeech": "VBN", "CharacterOffsetBegin": 879, "CharacterOffsetEnd": 883}], ["an", {"PartOfSpeech": "DT", "CharacterOffsetBegin": 884, "CharacterOffsetEnd": 886}], ["adverse", {"PartOfSpeech": "JJ", "CharacterOffsetBegin": 887, "CharacterOffsetEnd": 894}], ["net-benefit", {"PartOfSpeech": "JJ", "CharacterOffsetBegin": 895, "CharacterOffsetEnd": 906}], ["decision", {"PartOfSpeech": "NN", "CharacterOffsetBegin": 907, "CharacterOffsetEnd": 915}], ["about", {"PartOfSpeech": "IN", "CharacterOffsetBegin": 916, "CharacterOffsetEnd": 921}], ["the", {"PartOfSpeech": "DT", "CharacterOffsetBegin": 922, "CharacterOffsetEnd": 925}], ["acquisition", {"PartOfSpeech": "NN", "CharacterOffsetBegin": 926, "CharacterOffsetEnd": 937}], ["of", {"PartOfSpeech": "IN", "CharacterOffsetBegin": 938, "CharacterOffsetEnd": 940}], ["a", {"PartOfSpeech": "DT", "CharacterOffsetBegin": 941, "CharacterOffsetEnd": 942}], ["publicly", {"PartOfSpeech": "RB", "CharacterOffsetBegin": 943, "CharacterOffsetEnd": 951}], ["traded", {"PartOfSpeech": "VBN", "CharacterOffsetBegin": 952, "CharacterOffsetEnd": 958}], ["company", {"PartOfSpeech": "NN", "CharacterOffsetBegin": 959, "CharacterOffsetEnd": 966}], [".", {"PartOfSpeech": ".", "CharacterOffsetBegin": 966, "CharacterOffsetEnd": 967}]]}, {"parsetree": "( (S (NP (PRP He)) (VP (VBD said) (SBAR (S (NP (PRP it)) (VP (VP (VBZ has) (VP (VBN reached) (NP (DT the) (JJ same) (NNS conclusions)) (PP (IN about) (NP (DT some) (NNS attempts))) (S (VP (TO to) (VP (VB buy) (NP (ADJP (RB closely) (VBN held)) (NNS concerns))))))) (, ,) (CC but) (VP (ADVP (RB eventually)) (VBD allowed) (NP (DT those) (NNS acquisitions)) (S (VP (TO to) (VP (VB proceed))))))))) (. .)))", "dependencies": [["root", "ROOT-0", "said-2"], ["nsubj", "said-2", "He-1"], ["nsubj", "reached-5", "it-3"], ["aux", "reached-5", "has-4"], ["ccomp", "said-2", "reached-5"], ["det", "conclusions-8", "the-6"], ["amod", "conclusions-8", "same-7"], ["dobj", "reached-5", "conclusions-8"], ["case", "attempts-11", "about-9"], ["det", "attempts-11", "some-10"], ["nmod", "reached-5", "attempts-11"], ["mark", "buy-13", "to-12"], ["advcl", "reached-5", "buy-13"], ["advmod", "held-15", "closely-14"], ["amod", "concerns-16", "held-15"], ["dobj", "buy-13", "concerns-16"], ["punct", "reached-5", ",-17"], ["cc", "reached-5", "but-18"], ["advmod", "allowed-20", "eventually-19"], ["conj", "reached-5", "allowed-20"], ["det", "acquisitions-22", "those-21"], ["dobj", "allowed-20", "acquisitions-22"], ["mark", "proceed-24", "to-23"], ["xcomp", "allowed-20", "proceed-24"], ["punct", "said-2", ".-25"]], "words": [["He", {"PartOfSpeech": "PRP", "CharacterOffsetBegin": 968, "CharacterOffsetEnd": 970}], ["said", {"PartOfSpeech": "VBD", "CharacterOffsetBegin": 971, "CharacterOffsetEnd": 975}], ["it", {"PartOfSpeech": "PRP", "CharacterOffsetBegin": 976, "CharacterOffsetEnd": 978}], ["has", {"PartOfSpeech": "VBZ", "CharacterOffsetBegin": 979, "CharacterOffsetEnd": 982}], ["reached", {"PartOfSpeech": "VBN", "CharacterOffsetBegin": 983, "CharacterOffsetEnd": 990}], ["the", {"PartOfSpeech": "DT", "CharacterOffsetBegin": 991, "CharacterOffsetEnd": 994}], ["same", {"PartOfSpeech": "JJ", "CharacterOffsetBegin": 995, "CharacterOffsetEnd": 999}], ["conclusions", {"PartOfSpeech": "NNS", "CharacterOffsetBegin": 1000, "CharacterOffsetEnd": 1011}], ["about", {"PartOfSpeech": "IN", "CharacterOffsetBegin": 1012, "CharacterOffsetEnd": 1017}], ["some", {"PartOfSpeech": "DT", "CharacterOffsetBegin": 1018, "CharacterOffsetEnd": 1022}], ["attempts", {"PartOfSpeech": "NNS", "CharacterOffsetBegin": 1023, "CharacterOffsetEnd": 1031}], ["to", {"PartOfSpeech": "TO", "CharacterOffsetBegin": 1032, "CharacterOffsetEnd": 1034}], ["buy", {"PartOfSpeech": "VB", "CharacterOffsetBegin": 1035, "CharacterOffsetEnd": 1038}], ["closely", {"PartOfSpeech": "RB", "CharacterOffsetBegin": 1039, "CharacterOffsetEnd": 1046}], ["held", {"PartOfSpeech": "VBN", "CharacterOffsetBegin": 1047, "CharacterOffsetEnd": 1051}], ["concerns", {"PartOfSpeech": "NNS", "CharacterOffsetBegin": 1052, "CharacterOffsetEnd": 1060}], [",", {"PartOfSpeech": ",", "CharacterOffsetBegin": 1060, "CharacterOffsetEnd": 1061}], ["but", {"PartOfSpeech": "CC", "CharacterOffsetBegin": 1062, "CharacterOffsetEnd": 1065}], ["eventually", {"PartOfSpeech": "RB", "CharacterOffsetBegin": 1066, "CharacterOffsetEnd": 1076}], ["allowed", {"PartOfSpeech": "VBD", "CharacterOffsetBegin": 1077, "CharacterOffsetEnd": 1084}], ["those", {"PartOfSpeech": "DT", "CharacterOffsetBegin": 1085, "CharacterOffsetEnd": 1090}], ["acquisitions", {"PartOfSpeech": "NNS", "CharacterOffsetBegin": 1091, "CharacterOffsetEnd": 1103}], ["to", {"PartOfSpeech": "TO", "CharacterOffsetBegin": 1104, "CharacterOffsetEnd": 1106}], ["proceed", {"PartOfSpeech": "VB", "CharacterOffsetBegin": 1107, "CharacterOffsetEnd": 1114}], [".", {"PartOfSpeech": ".", "CharacterOffsetBegin": 1114, "CharacterOffsetEnd": 1115}]]}, {"parsetree": "( (SINV (`` ``) (S (S (NP (DT This)) (VP (VBZ is) (RB n't) (NP (NP (DT a) (NN change)) (PP (IN in) (NP (NN government) (NN policy)))))) (: ;) (S (NP (DT this) (NN provision)) (VP (VBZ has) (VP (VBN been) (VP (VBN used) (PP (IN before))))))) (, ,) ('' '') (VP (VBD said)) (NP (NP (NNP Jodi) (NNP Redmond)) (, ,) (NP (NP (NN press) (NN secretary)) (PP (IN for) (NP (NP (NNP Harvie) (NNP Andre)) (, ,) (NP (NP (NP (NNP Canada) (POS 's)) (NN minister)) (PP (IN of) (NP (NN industry) (, ,) (NN science) (CC and) (NN technology)))))))) (. .)))", "dependencies": [["root", "ROOT-0", "said-19"], ["punct", "said-19", "``-1"], ["nsubj", "change-6", "This-2"], ["cop", "change-6", "is-3"], ["neg", "change-6", "n't-4"], ["det", "change-6", "a-5"], ["ccomp", "said-19", "change-6"], ["case", "policy-9", "in-7"], ["compound", "policy-9", "government-8"], ["nmod", "change-6", "policy-9"], ["punct", "change-6", ";-10"], ["det", "provision-12", "this-11"], ["nsubjpass", "used-15", "provision-12"], ["aux", "used-15", "has-13"], ["auxpass", "used-15", "been-14"], ["parataxis", "change-6", "used-15"], ["nmod", "used-15", "before-16"], ["punct", "said-19", ",-17"], ["punct", "said-19", "''-18"], ["compound", "Redmond-21", "Jodi-20"], ["nsubj", "said-19", "Redmond-21"], ["punct", "Redmond-21", ",-22"], ["compound", "secretary-24", "press-23"], ["appos", "Redmond-21", "secretary-24"], ["case", "Andre-27", "for-25"], ["compound", "Andre-27", "Harvie-26"], ["nmod", "secretary-24", "Andre-27"], ["punct", "Andre-27", ",-28"], ["nmod:poss", "minister-31", "Canada-29"], ["case", "Canada-29", "'s-30"], ["appos", "Andre-27", "minister-31"], ["case", "industry-33", "of-32"], ["nmod", "minister-31", "industry-33"], ["punct", "industry-33", ",-34"], ["conj", "industry-33", "science-35"], ["cc", "industry-33", "and-36"], ["conj", "industry-33", "technology-37"], ["punct", "said-19", ".-38"]], "words": [["``", {"PartOfSpeech": "``", "CharacterOffsetBegin": 1118, "CharacterOffsetEnd": 1119}], ["This", {"PartOfSpeech": "DT", "CharacterOffsetBegin": 1119, "CharacterOffsetEnd": 1123}], ["is", {"PartOfSpeech": "VBZ", "CharacterOffsetBegin": 1124, "CharacterOffsetEnd": 1126}], ["n't", {"PartOfSpeech": "RB", "CharacterOffsetBegin": 1126, "CharacterOffsetEnd": 1129}], ["a", {"PartOfSpeech": "DT", "CharacterOffsetBegin": 1130, "CharacterOffsetEnd": 1131}], ["change", {"PartOfSpeech": "NN", "CharacterOffsetBegin": 1132, "CharacterOffsetEnd": 1138}], ["in", {"PartOfSpeech": "IN", "CharacterOffsetBegin": 1139, "CharacterOffsetEnd": 1141}], ["government", {"PartOfSpeech": "NN", "CharacterOffsetBegin": 1142, "CharacterOffsetEnd": 1152}], ["policy", {"PartOfSpeech": "NN", "CharacterOffsetBegin": 1153, "CharacterOffsetEnd": 1159}], [";", {"PartOfSpeech": ":", "CharacterOffsetBegin": 1159, "CharacterOffsetEnd": 1160}], ["this", {"PartOfSpeech": "DT", "CharacterOffsetBegin": 1161, "CharacterOffsetEnd": 1165}], ["provision", {"PartOfSpeech": "NN", "CharacterOffsetBegin": 1166, "CharacterOffsetEnd": 1175}], ["has", {"PartOfSpeech": "VBZ", "CharacterOffsetBegin": 1176, "CharacterOffsetEnd": 1179}], ["been", {"PartOfSpeech": "VBN", "CharacterOffsetBegin": 1180, "CharacterOffsetEnd": 1184}], ["used", {"PartOfSpeech": "VBN", "CharacterOffsetBegin": 1185, "CharacterOffsetEnd": 1189}], ["before", {"PartOfSpeech": "IN", "CharacterOffsetBegin": 1190, "CharacterOffsetEnd": 1196}], [",", {"PartOfSpeech": ",", "CharacterOffsetBegin": 1196, "CharacterOffsetEnd": 1197}], ["''", {"PartOfSpeech": "''", "CharacterOffsetBegin": 1197, "CharacterOffsetEnd": 1198}], ["said", {"PartOfSpeech": "VBD", "CharacterOffsetBegin": 1199, "CharacterOffsetEnd": 1203}], ["Jodi", {"PartOfSpeech": "NNP", "CharacterOffsetBegin": 1204, "CharacterOffsetEnd": 1208}], ["Redmond", {"PartOfSpeech": "NNP", "CharacterOffsetBegin": 1209, "CharacterOffsetEnd": 1216}], [",", {"PartOfSpeech": ",", "CharacterOffsetBegin": 1216, "CharacterOffsetEnd": 1217}], ["press", {"PartOfSpeech": "NN", "CharacterOffsetBegin": 1218, "CharacterOffsetEnd": 1223}], ["secretary", {"PartOfSpeech": "NN", "CharacterOffsetBegin": 1224, "CharacterOffsetEnd": 1233}], ["for", {"PartOfSpeech": "IN", "CharacterOffsetBegin": 1234, "CharacterOffsetEnd": 1237}], ["Harvie", {"PartOfSpeech": "NNP", "CharacterOffsetBegin": 1238, "CharacterOffsetEnd": 1244}], ["Andre", {"PartOfSpeech": "NNP", "CharacterOffsetBegin": 1245, "CharacterOffsetEnd": 1250}], [",", {"PartOfSpeech": ",", "CharacterOffsetBegin": 1250, "CharacterOffsetEnd": 1251}], ["Canada", {"PartOfSpeech": "NNP", "CharacterOffsetBegin": 1252, "CharacterOffsetEnd": 1258}], ["'s", {"PartOfSpeech": "POS", "CharacterOffsetBegin": 1258, "CharacterOffsetEnd": 1260}], ["minister", {"PartOfSpeech": "NN", "CharacterOffsetBegin": 1261, "CharacterOffsetEnd": 1269}], ["of", {"PartOfSpeech": "IN", "CharacterOffsetBegin": 1270, "CharacterOffsetEnd": 1272}], ["industry", {"PartOfSpeech": "NN", "CharacterOffsetBegin": 1273, "CharacterOffsetEnd": 1281}], [",", {"PartOfSpeech": ",", "CharacterOffsetBegin": 1281, "CharacterOffsetEnd": 1282}], ["science", {"PartOfSpeech": "NN", "CharacterOffsetBegin": 1283, "CharacterOffsetEnd": 1290}], ["and", {"PartOfSpeech": "CC", "CharacterOffsetBegin": 1291, "CharacterOffsetEnd": 1294}], ["technology", {"PartOfSpeech": "NN", "CharacterOffsetBegin": 1295, "CharacterOffsetEnd": 1305}], [".", {"PartOfSpeech": ".", "CharacterOffsetBegin": 1305, "CharacterOffsetEnd": 1306}]]}, {"parsetree": "( (S (NP (NNP Mr.) (NNP Andre)) (VP (VBD issued) (NP (DT the) (NN ruling)) (PP (VBN based) (PP (IN on) (NP (NP (DT a) (NN recommendation)) (PP (IN by) (NP (NNP Investment) (NNP Canada))))))) (. .)))", "dependencies": [["root", "ROOT-0", "issued-3"], ["compound", "Andre-2", "Mr.-1"], ["nsubj", "issued-3", "Andre-2"], ["det", "ruling-5", "the-4"], ["dobj", "issued-3", "ruling-5"], ["case", "recommendation-9", "based-6"], ["case", "recommendation-9", "on-7"], ["det", "recommendation-9", "a-8"], ["advcl", "issued-3", "recommendation-9"], ["case", "Canada-12", "by-10"], ["compound", "Canada-12", "Investment-11"], ["nmod", "recommendation-9", "Canada-12"], ["punct", "issued-3", ".-13"]], "words": [["Mr.", {"PartOfSpeech": "NNP", "CharacterOffsetBegin": 1307, "CharacterOffsetEnd": 1310}], ["Andre", {"PartOfSpeech": "NNP", "CharacterOffsetBegin": 1311, "CharacterOffsetEnd": 1316}], ["issued", {"PartOfSpeech": "VBD", "CharacterOffsetBegin": 1317, "CharacterOffsetEnd": 1323}], ["the", {"PartOfSpeech": "DT", "CharacterOffsetBegin": 1324, "CharacterOffsetEnd": 1327}], ["ruling", {"PartOfSpeech": "NN", "CharacterOffsetBegin": 1328, "CharacterOffsetEnd": 1334}], ["based", {"PartOfSpeech": "VBN", "CharacterOffsetBegin": 1335, "CharacterOffsetEnd": 1340}], ["on", {"PartOfSpeech": "IN", "CharacterOffsetBegin": 1341, "CharacterOffsetEnd": 1343}], ["a", {"PartOfSpeech": "DT", "CharacterOffsetBegin": 1344, "CharacterOffsetEnd": 1345}], ["recommendation", {"PartOfSpeech": "NN", "CharacterOffsetBegin": 1346, "CharacterOffsetEnd": 1360}], ["by", {"PartOfSpeech": "IN", "CharacterOffsetBegin": 1361, "CharacterOffsetEnd": 1363}], ["Investment", {"PartOfSpeech": "NNP", "CharacterOffsetBegin": 1364, "CharacterOffsetEnd": 1374}], ["Canada", {"PartOfSpeech": "NNP", "CharacterOffsetBegin": 1375, "CharacterOffsetEnd": 1381}], [".", {"PartOfSpeech": ".", "CharacterOffsetBegin": 1381, "CharacterOffsetEnd": 1382}]]}, {"parsetree": "( (S (NP (NP (NNS Spokesmen)) (PP (IN for) (NP (NNP Merieux) (CC and) (NNP Connaught)))) (VP (VBD said) (SBAR (S (NP (PRP they)) (VP (VP (VBD had) (RB n't) (VP (VBN been) (VP (VBN informed) (PP (IN of) (NP (NP (JJ specific) (NNS areas)) (PP (IN of) (NP (NN concern))))) (PP (IN by) (NP (CC either) (NP (DT the) (NN government)) (CC or) (NP (NN Investment) (NNP Canada))))))) (, ,) (CC but) (VP (VBD added) (SBAR (S (NP (PRP they)) (VP (VBP hope) (S (VP (TO to) (VP (VB have) (NP (JJR more) (NN information)) (NP-TMP (RB early) (DT this) (NN week))))))))))))) (. .)))", "dependencies": [["root", "ROOT-0", "said-6"], ["nsubj", "said-6", "Spokesmen-1"], ["case", "Merieux-3", "for-2"], ["nmod", "Spokesmen-1", "Merieux-3"], ["cc", "Merieux-3", "and-4"], ["conj", "Merieux-3", "Connaught-5"], ["nsubjpass", "informed-11", "they-7"], ["aux", "informed-11", "had-8"], ["neg", "informed-11", "n't-9"], ["auxpass", "informed-11", "been-10"], ["ccomp", "said-6", "informed-11"], ["case", "areas-14", "of-12"], ["amod", "areas-14", "specific-13"], ["nmod", "informed-11", "areas-14"], ["case", "concern-16", "of-15"], ["nmod", "areas-14", "concern-16"], ["case", "government-20", "by-17"], ["cc:preconj", "government-20", "either-18"], ["det", "government-20", "the-19"], ["nmod", "informed-11", "government-20"], ["cc", "government-20", "or-21"], ["compound", "Canada-23", "Investment-22"], ["conj", "government-20", "Canada-23"], ["punct", "informed-11", ",-24"], ["cc", "informed-11", "but-25"], ["conj", "informed-11", "added-26"], ["nsubj", "hope-28", "they-27"], ["ccomp", "added-26", "hope-28"], ["mark", "have-30", "to-29"], ["xcomp", "hope-28", "have-30"], ["amod", "information-32", "more-31"], ["dobj", "have-30", "information-32"], ["advmod", "week-35", "early-33"], ["det", "week-35", "this-34"], ["nmod:tmod", "have-30", "week-35"], ["punct", "said-6", ".-36"]], "words": [["Spokesmen", {"PartOfSpeech": "NNS", "CharacterOffsetBegin": 1385, "CharacterOffsetEnd": 1394}], ["for", {"PartOfSpeech": "IN", "CharacterOffsetBegin": 1395, "CharacterOffsetEnd": 1398}], ["Merieux", {"PartOfSpeech": "NNP", "CharacterOffsetBegin": 1399, "CharacterOffsetEnd": 1406}], ["and", {"PartOfSpeech": "CC", "CharacterOffsetBegin": 1407, "CharacterOffsetEnd": 1410}], ["Connaught", {"PartOfSpeech": "NNP", "CharacterOffsetBegin": 1411, "CharacterOffsetEnd": 1420}], ["said", {"PartOfSpeech": "VBD", "CharacterOffsetBegin": 1421, "CharacterOffsetEnd": 1425}], ["they", {"PartOfSpeech": "PRP", "CharacterOffsetBegin": 1426, "CharacterOffsetEnd": 1430}], ["had", {"PartOfSpeech": "VBD", "CharacterOffsetBegin": 1431, "CharacterOffsetEnd": 1434}], ["n't", {"PartOfSpeech": "RB", "CharacterOffsetBegin": 1434, "CharacterOffsetEnd": 1437}], ["been", {"PartOfSpeech": "VBN", "CharacterOffsetBegin": 1438, "CharacterOffsetEnd": 1442}], ["informed", {"PartOfSpeech": "VBN", "CharacterOffsetBegin": 1443, "CharacterOffsetEnd": 1451}], ["of", {"PartOfSpeech": "IN", "CharacterOffsetBegin": 1452, "CharacterOffsetEnd": 1454}], ["specific", {"PartOfSpeech": "JJ", "CharacterOffsetBegin": 1455, "CharacterOffsetEnd": 1463}], ["areas", {"PartOfSpeech": "NNS", "CharacterOffsetBegin": 1464, "CharacterOffsetEnd": 1469}], ["of", {"PartOfSpeech": "IN", "CharacterOffsetBegin": 1470, "CharacterOffsetEnd": 1472}], ["concern", {"PartOfSpeech": "NN", "CharacterOffsetBegin": 1473, "CharacterOffsetEnd": 1480}], ["by", {"PartOfSpeech": "IN", "CharacterOffsetBegin": 1481, "CharacterOffsetEnd": 1483}], ["either", {"PartOfSpeech": "CC", "CharacterOffsetBegin": 1484, "CharacterOffsetEnd": 1490}], ["the", {"PartOfSpeech": "DT", "CharacterOffsetBegin": 1491, "CharacterOffsetEnd": 1494}], ["government", {"PartOfSpeech": "NN", "CharacterOffsetBegin": 1495, "CharacterOffsetEnd": 1505}], ["or", {"PartOfSpeech": "CC", "CharacterOffsetBegin": 1506, "CharacterOffsetEnd": 1508}], ["Investment", {"PartOfSpeech": "NN", "CharacterOffsetBegin": 1509, "CharacterOffsetEnd": 1519}], ["Canada", {"PartOfSpeech": "NNP", "CharacterOffsetBegin": 1520, "CharacterOffsetEnd": 1526}], [",", {"PartOfSpeech": ",", "CharacterOffsetBegin": 1526, "CharacterOffsetEnd": 1527}], ["but", {"PartOfSpeech": "CC", "CharacterOffsetBegin": 1528, "CharacterOffsetEnd": 1531}], ["added", {"PartOfSpeech": "VBD", "CharacterOffsetBegin": 1532, "CharacterOffsetEnd": 1537}], ["they", {"PartOfSpeech": "PRP", "CharacterOffsetBegin": 1538, "CharacterOffsetEnd": 1542}], ["hope", {"PartOfSpeech": "VBP", "CharacterOffsetBegin": 1543, "CharacterOffsetEnd": 1547}], ["to", {"PartOfSpeech": "TO", "CharacterOffsetBegin": 1548, "CharacterOffsetEnd": 1550}], ["have", {"PartOfSpeech": "VB", "CharacterOffsetBegin": 1551, "CharacterOffsetEnd": 1555}], ["more", {"PartOfSpeech": "JJR", "CharacterOffsetBegin": 1556, "CharacterOffsetEnd": 1560}], ["information", {"PartOfSpeech": "NN", "CharacterOffsetBegin": 1561, "CharacterOffsetEnd": 1572}], ["early", {"PartOfSpeech": "RB", "CharacterOffsetBegin": 1573, "CharacterOffsetEnd": 1578}], ["this", {"PartOfSpeech": "DT", "CharacterOffsetBegin": 1579, "CharacterOffsetEnd": 1583}], ["week", {"PartOfSpeech": "NN", "CharacterOffsetBegin": 1584, "CharacterOffsetEnd": 1588}], [".", {"PartOfSpeech": ".", "CharacterOffsetBegin": 1588, "CharacterOffsetEnd": 1589}]]}, {"parsetree": "( (S (NP (NNP Investment) (NNP Canada)) (VP (VBD declined) (S (VP (TO to) (VP (VB comment) (PP (IN on) (NP (NP (DT the) (NNS reasons)) (PP (IN for) (NP (DT the) (NN government) (NN decision))))))))) (. .)))", "dependencies": [["root", "ROOT-0", "declined-3"], ["compound", "Canada-2", "Investment-1"], ["nsubj", "declined-3", "Canada-2"], ["mark", "comment-5", "to-4"], ["xcomp", "declined-3", "comment-5"], ["case", "reasons-8", "on-6"], ["det", "reasons-8", "the-7"], ["nmod", "comment-5", "reasons-8"], ["case", "decision-12", "for-9"], ["det", "decision-12", "the-10"], ["compound", "decision-12", "government-11"], ["nmod", "reasons-8", "decision-12"], ["punct", "declined-3", ".-13"]], "words": [["Investment", {"PartOfSpeech": "NNP", "CharacterOffsetBegin": 1592, "CharacterOffsetEnd": 1602}], ["Canada", {"PartOfSpeech": "NNP", "CharacterOffsetBegin": 1603, "CharacterOffsetEnd": 1609}], ["declined", {"PartOfSpeech": "VBD", "CharacterOffsetBegin": 1610, "CharacterOffsetEnd": 1618}], ["to", {"PartOfSpeech": "TO", "CharacterOffsetBegin": 1619, "CharacterOffsetEnd": 1621}], ["comment", {"PartOfSpeech": "VB", "CharacterOffsetBegin": 1622, "CharacterOffsetEnd": 1629}], ["on", {"PartOfSpeech": "IN", "CharacterOffsetBegin": 1630, "CharacterOffsetEnd": 1632}], ["the", {"PartOfSpeech": "DT", "CharacterOffsetBegin": 1633, "CharacterOffsetEnd": 1636}], ["reasons", {"PartOfSpeech": "NNS", "CharacterOffsetBegin": 1637, "CharacterOffsetEnd": 1644}], ["for", {"PartOfSpeech": "IN", "CharacterOffsetBegin": 1645, "CharacterOffsetEnd": 1648}], ["the", {"PartOfSpeech": "DT", "CharacterOffsetBegin": 1649, "CharacterOffsetEnd": 1652}], ["government", {"PartOfSpeech": "NN", "CharacterOffsetBegin": 1653, "CharacterOffsetEnd": 1663}], ["decision", {"PartOfSpeech": "NN", "CharacterOffsetBegin": 1664, "CharacterOffsetEnd": 1672}], [".", {"PartOfSpeech": ".", "CharacterOffsetBegin": 1672, "CharacterOffsetEnd": 1673}]]}, {"parsetree": "( (S (NP (NP (NNP Viren) (NNP Mehta)) (, ,) (NP (NP (DT a) (NN partner)) (PP (IN with) (NP (NP (NNP Mehta) (CC &) (NNP Isaly)) (, ,) (NP (DT a) (ADJP (NNP New) (JJ York-based)) (JJ pharmaceutical) (NN industry) (NN research) (NN firm))))) (, ,)) (VP (VBD said) (SBAR (S (NP (NP (DT the) (NN government) (POS 's)) (NN ruling)) (VP (VBD was) (RB n't) (ADJP (JJ unexpected)))))) (. .)))", "dependencies": [["root", "ROOT-0", "said-19"], ["compound", "Mehta-2", "Viren-1"], ["nsubj", "said-19", "Mehta-2"], ["punct", "Mehta-2", ",-3"], ["det", "partner-5", "a-4"], ["appos", "Mehta-2", "partner-5"], ["case", "Mehta-7", "with-6"], ["nmod", "partner-5", "Mehta-7"], ["cc", "Mehta-7", "&-8"], ["conj", "Mehta-7", "Isaly-9"], ["punct", "Mehta-7", ",-10"], ["det", "firm-17", "a-11"], ["amod", "York-based-13", "New-12"], ["amod", "firm-17", "York-based-13"], ["amod", "firm-17", "pharmaceutical-14"], ["compound", "firm-17", "industry-15"], ["compound", "firm-17", "research-16"], ["appos", "Mehta-7", "firm-17"], ["punct", "Mehta-2", ",-18"], ["det", "government-21", "the-20"], ["nmod:poss", "ruling-23", "government-21"], ["case", "government-21", "'s-22"], ["nsubj", "unexpected-26", "ruling-23"], ["cop", "unexpected-26", "was-24"], ["neg", "unexpected-26", "n't-25"], ["ccomp", "said-19", "unexpected-26"], ["punct", "said-19", ".-27"]], "words": [["Viren", {"PartOfSpeech": "NNP", "CharacterOffsetBegin": 1676, "CharacterOffsetEnd": 1681}], ["Mehta", {"PartOfSpeech": "NNP", "CharacterOffsetBegin": 1682, "CharacterOffsetEnd": 1687}], [",", {"PartOfSpeech": ",", "CharacterOffsetBegin": 1687, "CharacterOffsetEnd": 1688}], ["a", {"PartOfSpeech": "DT", "CharacterOffsetBegin": 1689, "CharacterOffsetEnd": 1690}], ["partner", {"PartOfSpeech": "NN", "CharacterOffsetBegin": 1691, "CharacterOffsetEnd": 1698}], ["with", {"PartOfSpeech": "IN", "CharacterOffsetBegin": 1699, "CharacterOffsetEnd": 1703}], ["Mehta", {"PartOfSpeech": "NNP", "CharacterOffsetBegin": 1704, "CharacterOffsetEnd": 1709}], ["&", {"PartOfSpeech": "CC", "CharacterOffsetBegin": 1710, "CharacterOffsetEnd": 1711}], ["Isaly", {"PartOfSpeech": "NNP", "CharacterOffsetBegin": 1712, "CharacterOffsetEnd": 1717}], [",", {"PartOfSpeech": ",", "CharacterOffsetBegin": 1717, "CharacterOffsetEnd": 1718}], ["a", {"PartOfSpeech": "DT", "CharacterOffsetBegin": 1719, "CharacterOffsetEnd": 1720}], ["New", {"PartOfSpeech": "NNP", "CharacterOffsetBegin": 1721, "CharacterOffsetEnd": 1724}], ["York-based", {"PartOfSpeech": "JJ", "CharacterOffsetBegin": 1725, "CharacterOffsetEnd": 1735}], ["pharmaceutical", {"PartOfSpeech": "JJ", "CharacterOffsetBegin": 1736, "CharacterOffsetEnd": 1750}], ["industry", {"PartOfSpeech": "NN", "CharacterOffsetBegin": 1751, "CharacterOffsetEnd": 1759}], ["research", {"PartOfSpeech": "NN", "CharacterOffsetBegin": 1760, "CharacterOffsetEnd": 1768}], ["firm", {"PartOfSpeech": "NN", "CharacterOffsetBegin": 1769, "CharacterOffsetEnd": 1773}], [",", {"PartOfSpeech": ",", "CharacterOffsetBegin": 1773, "CharacterOffsetEnd": 1774}], ["said", {"PartOfSpeech": "VBD", "CharacterOffsetBegin": 1775, "CharacterOffsetEnd": 1779}], ["the", {"PartOfSpeech": "DT", "CharacterOffsetBegin": 1780, "CharacterOffsetEnd": 1783}], ["government", {"PartOfSpeech": "NN", "CharacterOffsetBegin": 1784, "CharacterOffsetEnd": 1794}], ["'s", {"PartOfSpeech": "POS", "CharacterOffsetBegin": 1794, "CharacterOffsetEnd": 1796}], ["ruling", {"PartOfSpeech": "NN", "CharacterOffsetBegin": 1797, "CharacterOffsetEnd": 1803}], ["was", {"PartOfSpeech": "VBD", "CharacterOffsetBegin": 1804, "CharacterOffsetEnd": 1807}], ["n't", {"PartOfSpeech": "RB", "CharacterOffsetBegin": 1807, "CharacterOffsetEnd": 1810}], ["unexpected", {"PartOfSpeech": "JJ", "CharacterOffsetBegin": 1811, "CharacterOffsetEnd": 1821}], [".", {"PartOfSpeech": ".", "CharacterOffsetBegin": 1821, "CharacterOffsetEnd": 1822}]]}, {"parsetree": "( (S (`` ``) (S (NP (DT This)) (VP (VBZ has) (VP (VBN become) (NP (DT a) (ADJP (RB very) (VBN politicized)) (NN deal))) (, ,) (PP (VBG concerning) (NP (NP (NP (NNP Canada) (POS 's)) (ADJP (RB only) (JJ large)) (, ,) (JJ world-class) (NN bio-research)) (CC or) (NP (JJ pharmaceutical) (NN company)))))) (, ,) ('' '') (NP (NNP Mr.) (NNP Mehta)) (VP (VBD said)) (. .)))", "dependencies": [["root", "ROOT-0", "said-25"], ["punct", "said-25", "``-1"], ["nsubj", "become-4", "This-2"], ["aux", "become-4", "has-3"], ["ccomp", "said-25", "become-4"], ["det", "deal-8", "a-5"], ["advmod", "politicized-7", "very-6"], ["amod", "deal-8", "politicized-7"], ["xcomp", "become-4", "deal-8"], ["punct", "become-4", ",-9"], ["case", "bio-research-17", "concerning-10"], ["nmod:poss", "bio-research-17", "Canada-11"], ["case", "Canada-11", "'s-12"], ["advmod", "large-14", "only-13"], ["amod", "bio-research-17", "large-14"], ["punct", "bio-research-17", ",-15"], ["amod", "bio-research-17", "world-class-16"], ["nmod", "become-4", "bio-research-17"], ["cc", "bio-research-17", "or-18"], ["amod", "company-20", "pharmaceutical-19"], ["conj", "bio-research-17", "company-20"], ["punct", "said-25", ",-21"], ["punct", "said-25", "''-22"], ["compound", "Mehta-24", "Mr.-23"], ["nsubj", "said-25", "Mehta-24"], ["punct", "said-25", ".-26"]], "words": [["``", {"PartOfSpeech": "``", "CharacterOffsetBegin": 1825, "CharacterOffsetEnd": 1826}], ["This", {"PartOfSpeech": "DT", "CharacterOffsetBegin": 1826, "CharacterOffsetEnd": 1830}], ["has", {"PartOfSpeech": "VBZ", "CharacterOffsetBegin": 1831, "CharacterOffsetEnd": 1834}], ["become", {"PartOfSpeech": "VBN", "CharacterOffsetBegin": 1835, "CharacterOffsetEnd": 1841}], ["a", {"PartOfSpeech": "DT", "CharacterOffsetBegin": 1842, "CharacterOffsetEnd": 1843}], ["very", {"PartOfSpeech": "RB", "CharacterOffsetBegin": 1844, "CharacterOffsetEnd": 1848}], ["politicized", {"PartOfSpeech": "VBN", "CharacterOffsetBegin": 1849, "CharacterOffsetEnd": 1860}], ["deal", {"PartOfSpeech": "NN", "CharacterOffsetBegin": 1861, "CharacterOffsetEnd": 1865}], [",", {"PartOfSpeech": ",", "CharacterOffsetBegin": 1865, "CharacterOffsetEnd": 1866}], ["concerning", {"PartOfSpeech": "VBG", "CharacterOffsetBegin": 1867, "CharacterOffsetEnd": 1877}], ["Canada", {"PartOfSpeech": "NNP", "CharacterOffsetBegin": 1878, "CharacterOffsetEnd": 1884}], ["'s", {"PartOfSpeech": "POS", "CharacterOffsetBegin": 1884, "CharacterOffsetEnd": 1886}], ["only", {"PartOfSpeech": "RB", "CharacterOffsetBegin": 1887, "CharacterOffsetEnd": 1891}], ["large", {"PartOfSpeech": "JJ", "CharacterOffsetBegin": 1892, "CharacterOffsetEnd": 1897}], [",", {"PartOfSpeech": ",", "CharacterOffsetBegin": 1897, "CharacterOffsetEnd": 1898}], ["world-class", {"PartOfSpeech": "JJ", "CharacterOffsetBegin": 1899, "CharacterOffsetEnd": 1910}], ["bio-research", {"PartOfSpeech": "NN", "CharacterOffsetBegin": 1911, "CharacterOffsetEnd": 1923}], ["or", {"PartOfSpeech": "CC", "CharacterOffsetBegin": 1924, "CharacterOffsetEnd": 1926}], ["pharmaceutical", {"PartOfSpeech": "JJ", "CharacterOffsetBegin": 1927, "CharacterOffsetEnd": 1941}], ["company", {"PartOfSpeech": "NN", "CharacterOffsetBegin": 1942, "CharacterOffsetEnd": 1949}], [",", {"PartOfSpeech": ",", "CharacterOffsetBegin": 1949, "CharacterOffsetEnd": 1950}], ["''", {"PartOfSpeech": "''", "CharacterOffsetBegin": 1950, "CharacterOffsetEnd": 1951}], ["Mr.", {"PartOfSpeech": "NNP", "CharacterOffsetBegin": 1952, "CharacterOffsetEnd": 1955}], ["Mehta", {"PartOfSpeech": "NNP", "CharacterOffsetBegin": 1956, "CharacterOffsetEnd": 1961}], ["said", {"PartOfSpeech": "VBD", "CharacterOffsetBegin": 1962, "CharacterOffsetEnd": 1966}], [".", {"PartOfSpeech": ".", "CharacterOffsetBegin": 1966, "CharacterOffsetEnd": 1967}]]}, {"parsetree": "( (S (NP (NNP Mr.) (NNP Mehta)) (VP (VBD said) (NP (NP (DT the) (NN move)) (SBAR (WHNP (WDT that)) (S (VP (MD could) (VP (VB allow) (NP (DT the) (NN transaction) (S (VP (TO to) (VP (VB go) (ADVP (RB ahead)) (SBAR (IN as) (S (NP (VBN planned)) (VP (MD could) (VP (VB be) (NP (NP (DT an) (JJ out-of-court) (NN settlement)) (PP (IN of) (NP (NP (NNP Connaught) (POS 's)) (NN dispute)))) (PP (IN with) (NP (NP (DT the) (NNP University)) (PP (IN of) (NP (NNP Toronto))))))))))))))))))) (. .)))", "dependencies": [["root", "ROOT-0", "said-3"], ["compound", "Mehta-2", "Mr.-1"], ["nsubj", "said-3", "Mehta-2"], ["det", "move-5", "the-4"], ["dobj", "said-3", "move-5"], ["nsubj", "allow-8", "that-6"], ["aux", "allow-8", "could-7"], ["acl:relcl", "move-5", "allow-8"], ["det", "transaction-10", "the-9"], ["dobj", "allow-8", "transaction-10"], ["mark", "go-12", "to-11"], ["acl", "transaction-10", "go-12"], ["advmod", "go-12", "ahead-13"], ["mark", "settlement-20", "as-14"], ["nsubj", "settlement-20", "planned-15"], ["aux", "settlement-20", "could-16"], ["cop", "settlement-20", "be-17"], ["det", "settlement-20", "an-18"], ["amod", "settlement-20", "out-of-court-19"], ["advcl", "go-12", "settlement-20"], ["case", "dispute-24", "of-21"], ["nmod:poss", "dispute-24", "Connaught-22"], ["case", "Connaught-22", "'s-23"], ["nmod", "settlement-20", "dispute-24"], ["case", "University-27", "with-25"], ["det", "University-27", "the-26"], ["nmod", "settlement-20", "University-27"], ["case", "Toronto-29", "of-28"], ["nmod", "University-27", "Toronto-29"], ["punct", "said-3", ".-30"]], "words": [["Mr.", {"PartOfSpeech": "NNP", "CharacterOffsetBegin": 1970, "CharacterOffsetEnd": 1973}], ["Mehta", {"PartOfSpeech": "NNP", "CharacterOffsetBegin": 1974, "CharacterOffsetEnd": 1979}], ["said", {"PartOfSpeech": "VBD", "CharacterOffsetBegin": 1980, "CharacterOffsetEnd": 1984}], ["the", {"PartOfSpeech": "DT", "CharacterOffsetBegin": 1985, "CharacterOffsetEnd": 1988}], ["move", {"PartOfSpeech": "NN", "CharacterOffsetBegin": 1989, "CharacterOffsetEnd": 1993}], ["that", {"PartOfSpeech": "WDT", "CharacterOffsetBegin": 1994, "CharacterOffsetEnd": 1998}], ["could", {"PartOfSpeech": "MD", "CharacterOffsetBegin": 1999, "CharacterOffsetEnd": 2004}], ["allow", {"PartOfSpeech": "VB", "CharacterOffsetBegin": 2005, "CharacterOffsetEnd": 2010}], ["the", {"PartOfSpeech": "DT", "CharacterOffsetBegin": 2011, "CharacterOffsetEnd": 2014}], ["transaction", {"PartOfSpeech": "NN", "CharacterOffsetBegin": 2015, "CharacterOffsetEnd": 2026}], ["to", {"PartOfSpeech": "TO", "CharacterOffsetBegin": 2027, "CharacterOffsetEnd": 2029}], ["go", {"PartOfSpeech": "VB", "CharacterOffsetBegin": 2030, "CharacterOffsetEnd": 2032}], ["ahead", {"PartOfSpeech": "RB", "CharacterOffsetBegin": 2033, "CharacterOffsetEnd": 2038}], ["as", {"PartOfSpeech": "IN", "CharacterOffsetBegin": 2039, "CharacterOffsetEnd": 2041}], ["planned", {"PartOfSpeech": "VBN", "CharacterOffsetBegin": 2042, "CharacterOffsetEnd": 2049}], ["could", {"PartOfSpeech": "MD", "CharacterOffsetBegin": 2050, "CharacterOffsetEnd": 2055}], ["be", {"PartOfSpeech": "VB", "CharacterOffsetBegin": 2056, "CharacterOffsetEnd": 2058}], ["an", {"PartOfSpeech": "DT", "CharacterOffsetBegin": 2059, "CharacterOffsetEnd": 2061}], ["out-of-court", {"PartOfSpeech": "JJ", "CharacterOffsetBegin": 2062, "CharacterOffsetEnd": 2074}], ["settlement", {"PartOfSpeech": "NN", "CharacterOffsetBegin": 2075, "CharacterOffsetEnd": 2085}], ["of", {"PartOfSpeech": "IN", "CharacterOffsetBegin": 2086, "CharacterOffsetEnd": 2088}], ["Connaught", {"PartOfSpeech": "NNP", "CharacterOffsetBegin": 2089, "CharacterOffsetEnd": 2098}], ["'s", {"PartOfSpeech": "POS", "CharacterOffsetBegin": 2098, "CharacterOffsetEnd": 2100}], ["dispute", {"PartOfSpeech": "NN", "CharacterOffsetBegin": 2101, "CharacterOffsetEnd": 2108}], ["with", {"PartOfSpeech": "IN", "CharacterOffsetBegin": 2109, "CharacterOffsetEnd": 2113}], ["the", {"PartOfSpeech": "DT", "CharacterOffsetBegin": 2114, "CharacterOffsetEnd": 2117}], ["University", {"PartOfSpeech": "NNP", "CharacterOffsetBegin": 2118, "CharacterOffsetEnd": 2128}], ["of", {"PartOfSpeech": "IN", "CharacterOffsetBegin": 2129, "CharacterOffsetEnd": 2131}], ["Toronto", {"PartOfSpeech": "NNP", "CharacterOffsetBegin": 2132, "CharacterOffsetEnd": 2139}], [".", {"PartOfSpeech": ".", "CharacterOffsetBegin": 2139, "CharacterOffsetEnd": 2140}]]}, {"parsetree": "( (S (NP (DT The) (NNP University)) (VP (VBZ is) (VP (VBG seeking) (S (VP (TO to) (VP (VB block) (NP (NP (DT the) (NN acquisition)) (PP (IN of) (NP (NNP Connaught)))) (PP (IN by) (NP (JJ foreign) (NNS interests))) (, ,) (S (VP (VBG citing) (NP (NP (NNS concerns)) (PP (IN about) (NP (NP (DT the) (NN amount)) (PP (IN of) (NP (NN research))))) (SBAR (WHNP (WDT that)) (S (VP (MD would) (VP (VB be) (VP (VBN done) (PP (IN in) (NP (NNP Canada)))))))))))))))) (. .)))", "dependencies": [["root", "ROOT-0", "seeking-4"], ["det", "University-2", "The-1"], ["nsubj", "seeking-4", "University-2"], ["aux", "seeking-4", "is-3"], ["mark", "block-6", "to-5"], ["xcomp", "seeking-4", "block-6"], ["det", "acquisition-8", "the-7"], ["dobj", "block-6", "acquisition-8"], ["case", "Connaught-10", "of-9"], ["nmod", "acquisition-8", "Connaught-10"], ["case", "interests-13", "by-11"], ["amod", "interests-13", "foreign-12"], ["nmod", "block-6", "interests-13"], ["punct", "block-6", ",-14"], ["advcl", "block-6", "citing-15"], ["dobj", "citing-15", "concerns-16"], ["case", "amount-19", "about-17"], ["det", "amount-19", "the-18"], ["nmod", "concerns-16", "amount-19"], ["case", "research-21", "of-20"], ["nmod", "amount-19", "research-21"], ["nsubjpass", "done-25", "that-22"], ["aux", "done-25", "would-23"], ["auxpass", "done-25", "be-24"], ["acl:relcl", "concerns-16", "done-25"], ["case", "Canada-27", "in-26"], ["nmod", "done-25", "Canada-27"], ["punct", "seeking-4", ".-28"]], "words": [["The", {"PartOfSpeech": "DT", "CharacterOffsetBegin": 2141, "CharacterOffsetEnd": 2144}], ["University", {"PartOfSpeech": "NNP", "CharacterOffsetBegin": 2145, "CharacterOffsetEnd": 2155}], ["is", {"PartOfSpeech": "VBZ", "CharacterOffsetBegin": 2156, "CharacterOffsetEnd": 2158}], ["seeking", {"PartOfSpeech": "VBG", "CharacterOffsetBegin": 2159, "CharacterOffsetEnd": 2166}], ["to", {"PartOfSpeech": "TO", "CharacterOffsetBegin": 2167, "CharacterOffsetEnd": 2169}], ["block", {"PartOfSpeech": "VB", "CharacterOffsetBegin": 2170, "CharacterOffsetEnd": 2175}], ["the", {"PartOfSpeech": "DT", "CharacterOffsetBegin": 2176, "CharacterOffsetEnd": 2179}], ["acquisition", {"PartOfSpeech": "NN", "CharacterOffsetBegin": 2180, "CharacterOffsetEnd": 2191}], ["of", {"PartOfSpeech": "IN", "CharacterOffsetBegin": 2192, "CharacterOffsetEnd": 2194}], ["Connaught", {"PartOfSpeech": "NNP", "CharacterOffsetBegin": 2195, "CharacterOffsetEnd": 2204}], ["by", {"PartOfSpeech": "IN", "CharacterOffsetBegin": 2205, "CharacterOffsetEnd": 2207}], ["foreign", {"PartOfSpeech": "JJ", "CharacterOffsetBegin": 2208, "CharacterOffsetEnd": 2215}], ["interests", {"PartOfSpeech": "NNS", "CharacterOffsetBegin": 2216, "CharacterOffsetEnd": 2225}], [",", {"PartOfSpeech": ",", "CharacterOffsetBegin": 2225, "CharacterOffsetEnd": 2226}], ["citing", {"PartOfSpeech": "VBG", "CharacterOffsetBegin": 2227, "CharacterOffsetEnd": 2233}], ["concerns", {"PartOfSpeech": "NNS", "CharacterOffsetBegin": 2234, "CharacterOffsetEnd": 2242}], ["about", {"PartOfSpeech": "IN", "CharacterOffsetBegin": 2243, "CharacterOffsetEnd": 2248}], ["the", {"PartOfSpeech": "DT", "CharacterOffsetBegin": 2249, "CharacterOffsetEnd": 2252}], ["amount", {"PartOfSpeech": "NN", "CharacterOffsetBegin": 2253, "CharacterOffsetEnd": 2259}], ["of", {"PartOfSpeech": "IN", "CharacterOffsetBegin": 2260, "CharacterOffsetEnd": 2262}], ["research", {"PartOfSpeech": "NN", "CharacterOffsetBegin": 2263, "CharacterOffsetEnd": 2271}], ["that", {"PartOfSpeech": "WDT", "CharacterOffsetBegin": 2272, "CharacterOffsetEnd": 2276}], ["would", {"PartOfSpeech": "MD", "CharacterOffsetBegin": 2277, "CharacterOffsetEnd": 2282}], ["be", {"PartOfSpeech": "VB", "CharacterOffsetBegin": 2283, "CharacterOffsetEnd": 2285}], ["done", {"PartOfSpeech": "VBN", "CharacterOffsetBegin": 2286, "CharacterOffsetEnd": 2290}], ["in", {"PartOfSpeech": "IN", "CharacterOffsetBegin": 2291, "CharacterOffsetEnd": 2293}], ["Canada", {"PartOfSpeech": "NNP", "CharacterOffsetBegin": 2294, "CharacterOffsetEnd": 2300}], [".", {"PartOfSpeech": ".", "CharacterOffsetBegin": 2300, "CharacterOffsetEnd": 2301}]]}, {"parsetree": "( (S (NP (DT The) (NN university)) (VP (VBZ is) (VP (VBG considering) (NP (NP (DT a) (NN settlement) (NN proposal)) (VP (VBN made) (PP (IN by) (NP (NNP Connaught))))))) (. .)))", "dependencies": [["root", "ROOT-0", "considering-4"], ["det", "university-2", "The-1"], ["nsubj", "considering-4", "university-2"], ["aux", "considering-4", "is-3"], ["det", "proposal-7", "a-5"], ["compound", "proposal-7", "settlement-6"], ["dobj", "considering-4", "proposal-7"], ["acl", "proposal-7", "made-8"], ["case", "Connaught-10", "by-9"], ["nmod", "made-8", "Connaught-10"], ["punct", "considering-4", ".-11"]], "words": [["The", {"PartOfSpeech": "DT", "CharacterOffsetBegin": 2304, "CharacterOffsetEnd": 2307}], ["university", {"PartOfSpeech": "NN", "CharacterOffsetBegin": 2308, "CharacterOffsetEnd": 2318}], ["is", {"PartOfSpeech": "VBZ", "CharacterOffsetBegin": 2319, "CharacterOffsetEnd": 2321}], ["considering", {"PartOfSpeech": "VBG", "CharacterOffsetBegin": 2322, "CharacterOffsetEnd": 2333}], ["a", {"PartOfSpeech": "DT", "CharacterOffsetBegin": 2334, "CharacterOffsetEnd": 2335}], ["settlement", {"PartOfSpeech": "NN", "CharacterOffsetBegin": 2336, "CharacterOffsetEnd": 2346}], ["proposal", {"PartOfSpeech": "NN", "CharacterOffsetBegin": 2347, "CharacterOffsetEnd": 2355}], ["made", {"PartOfSpeech": "VBN", "CharacterOffsetBegin": 2356, "CharacterOffsetEnd": 2360}], ["by", {"PartOfSpeech": "IN", "CharacterOffsetBegin": 2361, "CharacterOffsetEnd": 2363}], ["Connaught", {"PartOfSpeech": "NNP", "CharacterOffsetBegin": 2364, "CharacterOffsetEnd": 2373}], [".", {"PartOfSpeech": ".", "CharacterOffsetBegin": 2373, "CharacterOffsetEnd": 2374}]]}, {"parsetree": "( (S (SBAR (IN While) (S (NP (DT neither) (NN side)) (VP (MD will) (VP (VB disclose) (NP (PRP$ its) (NNS contents)))))) (, ,) (NP (NNP Mr.) (NNP Mehta)) (VP (VBZ expects) (S (NP (PRP it)) (VP (TO to) (VP (VB contain) (NP (NP (JJR more) (JJ specific) (NNS guarantees)) (PP (IN on) (NP (NN research) (CC and) (NN development) (NN spending) (NNS levels)))) (PP (IN in) (NP (NNP Canada))) (SBAR (IN than) (S (NP (NNP Merieux)) (VP (VBD offered) (PP (TO to) (NP (NNP Investment) (NNP Canada)))))))))) (. .)))", "dependencies": [["root", "ROOT-0", "expects-11"], ["mark", "disclose-5", "While-1"], ["det", "side-3", "neither-2"], ["nsubj", "disclose-5", "side-3"], ["aux", "disclose-5", "will-4"], ["advcl", "expects-11", "disclose-5"], ["nmod:poss", "contents-7", "its-6"], ["dobj", "disclose-5", "contents-7"], ["punct", "expects-11", ",-8"], ["compound", "Mehta-10", "Mr.-9"], ["nsubj", "expects-11", "Mehta-10"], ["dobj", "expects-11", "it-12"], ["mark", "contain-14", "to-13"], ["xcomp", "expects-11", "contain-14"], ["amod", "guarantees-17", "more-15"], ["amod", "guarantees-17", "specific-16"], ["dobj", "contain-14", "guarantees-17"], ["case", "levels-23", "on-18"], ["compound", "levels-23", "research-19"], ["cc", "research-19", "and-20"], ["conj", "research-19", "development-21"], ["compound", "levels-23", "spending-22"], ["nmod", "guarantees-17", "levels-23"], ["case", "Canada-25", "in-24"], ["nmod", "contain-14", "Canada-25"], ["mark", "offered-28", "than-26"], ["nsubj", "offered-28", "Merieux-27"], ["advcl", "contain-14", "offered-28"], ["case", "Canada-31", "to-29"], ["compound", "Canada-31", "Investment-30"], ["nmod", "offered-28", "Canada-31"], ["punct", "expects-11", ".-32"]], "words": [["While", {"PartOfSpeech": "IN", "CharacterOffsetBegin": 2375, "CharacterOffsetEnd": 2380}], ["neither", {"PartOfSpeech": "DT", "CharacterOffsetBegin": 2381, "CharacterOffsetEnd": 2388}], ["side", {"PartOfSpeech": "NN", "CharacterOffsetBegin": 2389, "CharacterOffsetEnd": 2393}], ["will", {"PartOfSpeech": "MD", "CharacterOffsetBegin": 2394, "CharacterOffsetEnd": 2398}], ["disclose", {"PartOfSpeech": "VB", "CharacterOffsetBegin": 2399, "CharacterOffsetEnd": 2407}], ["its", {"PartOfSpeech": "PRP$", "CharacterOffsetBegin": 2408, "CharacterOffsetEnd": 2411}], ["contents", {"PartOfSpeech": "NNS", "CharacterOffsetBegin": 2412, "CharacterOffsetEnd": 2420}], [",", {"PartOfSpeech": ",", "CharacterOffsetBegin": 2420, "CharacterOffsetEnd": 2421}], ["Mr.", {"PartOfSpeech": "NNP", "CharacterOffsetBegin": 2422, "CharacterOffsetEnd": 2425}], ["Mehta", {"PartOfSpeech": "NNP", "CharacterOffsetBegin": 2426, "CharacterOffsetEnd": 2431}], ["expects", {"PartOfSpeech": "VBZ", "CharacterOffsetBegin": 2432, "CharacterOffsetEnd": 2439}], ["it", {"PartOfSpeech": "PRP", "CharacterOffsetBegin": 2440, "CharacterOffsetEnd": 2442}], ["to", {"PartOfSpeech": "TO", "CharacterOffsetBegin": 2443, "CharacterOffsetEnd": 2445}], ["contain", {"PartOfSpeech": "VB", "CharacterOffsetBegin": 2446, "CharacterOffsetEnd": 2453}], ["more", {"PartOfSpeech": "JJR", "CharacterOffsetBegin": 2454, "CharacterOffsetEnd": 2458}], ["specific", {"PartOfSpeech": "JJ", "CharacterOffsetBegin": 2459, "CharacterOffsetEnd": 2467}], ["guarantees", {"PartOfSpeech": "NNS", "CharacterOffsetBegin": 2468, "CharacterOffsetEnd": 2478}], ["on", {"PartOfSpeech": "IN", "CharacterOffsetBegin": 2479, "CharacterOffsetEnd": 2481}], ["research", {"PartOfSpeech": "NN", "CharacterOffsetBegin": 2482, "CharacterOffsetEnd": 2490}], ["and", {"PartOfSpeech": "CC", "CharacterOffsetBegin": 2491, "CharacterOffsetEnd": 2494}], ["development", {"PartOfSpeech": "NN", "CharacterOffsetBegin": 2495, "CharacterOffsetEnd": 2506}], ["spending", {"PartOfSpeech": "NN", "CharacterOffsetBegin": 2507, "CharacterOffsetEnd": 2515}], ["levels", {"PartOfSpeech": "NNS", "CharacterOffsetBegin": 2516, "CharacterOffsetEnd": 2522}], ["in", {"PartOfSpeech": "IN", "CharacterOffsetBegin": 2523, "CharacterOffsetEnd": 2525}], ["Canada", {"PartOfSpeech": "NNP", "CharacterOffsetBegin": 2526, "CharacterOffsetEnd": 2532}], ["than", {"PartOfSpeech": "IN", "CharacterOffsetBegin": 2533, "CharacterOffsetEnd": 2537}], ["Merieux", {"PartOfSpeech": "NNP", "CharacterOffsetBegin": 2538, "CharacterOffsetEnd": 2545}], ["offered", {"PartOfSpeech": "VBD", "CharacterOffsetBegin": 2546, "CharacterOffsetEnd": 2553}], ["to", {"PartOfSpeech": "TO", "CharacterOffsetBegin": 2554, "CharacterOffsetEnd": 2556}], ["Investment", {"PartOfSpeech": "NNP", "CharacterOffsetBegin": 2557, "CharacterOffsetEnd": 2567}], ["Canada", {"PartOfSpeech": "NNP", "CharacterOffsetBegin": 2568, "CharacterOffsetEnd": 2574}], [".", {"PartOfSpeech": ".", "CharacterOffsetBegin": 2574, "CharacterOffsetEnd": 2575}]]}, {"parsetree": "( (S (NP (NP (DT Some) (NNS analysts)) (, ,) (PP (JJ such) (IN as) (NP (NP (NNP Murray) (NNP Grossner)) (PP (IN of) (NP (JJ Toronto-based) (NNP Richardson) (NNP Greenshields) (NNP Inc.))))) (, ,)) (VP (VBP believe) (SBAR (S (NP (DT the) (NN government) (NN ruling)) (VP (VBZ leaves) (NP (NP (DT the) (NN door)) (ADJP (JJ open) (PP (IN for) (NP (JJ other) (NNS bidders)))) (, ,) (PP (JJ such) (IN as) (NP (NP (NP (NNP Switzerland) (POS 's)) (NNP Ciba-Geigy) (CC and) (NNP Chiron) (NNP Corp.)) (PP (IN of) (NP (NNP Emeryville) (, ,) (NNP Calif.)))))))))) (. .)))", "dependencies": [["root", "ROOT-0", "believe-14"], ["det", "analysts-2", "Some-1"], ["nsubj", "believe-14", "analysts-2"], ["punct", "analysts-2", ",-3"], ["case", "Grossner-7", "such-4"], ["mwe", "such-4", "as-5"], ["compound", "Grossner-7", "Murray-6"], ["nmod", "analysts-2", "Grossner-7"], ["case", "Inc.-12", "of-8"], ["amod", "Inc.-12", "Toronto-based-9"], ["compound", "Inc.-12", "Richardson-10"], ["compound", "Inc.-12", "Greenshields-11"], ["nmod", "Grossner-7", "Inc.-12"], ["punct", "analysts-2", ",-13"], ["det", "ruling-17", "the-15"], ["compound", "ruling-17", "government-16"], ["nsubj", "leaves-18", "ruling-17"], ["ccomp", "believe-14", "leaves-18"], ["det", "door-20", "the-19"], ["dobj", "leaves-18", "door-20"], ["amod", "door-20", "open-21"], ["case", "bidders-24", "for-22"], ["amod", "bidders-24", "other-23"], ["nmod", "open-21", "bidders-24"], ["punct", "door-20", ",-25"], ["case", "Ciba-Geigy-30", "such-26"], ["mwe", "such-26", "as-27"], ["nmod:poss", "Ciba-Geigy-30", "Switzerland-28"], ["case", "Switzerland-28", "'s-29"], ["nmod", "door-20", "Ciba-Geigy-30"], ["cc", "Ciba-Geigy-30", "and-31"], ["compound", "Corp.-33", "Chiron-32"], ["conj", "Ciba-Geigy-30", "Corp.-33"], ["case", "Calif.-37", "of-34"], ["compound", "Calif.-37", "Emeryville-35"], ["punct", "Calif.-37", ",-36"], ["nmod", "Ciba-Geigy-30", "Calif.-37"], ["punct", "believe-14", ".-38"]], "words": [["Some", {"PartOfSpeech": "DT", "CharacterOffsetBegin": 2578, "CharacterOffsetEnd": 2582}], ["analysts", {"PartOfSpeech": "NNS", "CharacterOffsetBegin": 2583, "CharacterOffsetEnd": 2591}], [",", {"PartOfSpeech": ",", "CharacterOffsetBegin": 2591, "CharacterOffsetEnd": 2592}], ["such", {"PartOfSpeech": "JJ", "CharacterOffsetBegin": 2593, "CharacterOffsetEnd": 2597}], ["as", {"PartOfSpeech": "IN", "CharacterOffsetBegin": 2598, "CharacterOffsetEnd": 2600}], ["Murray", {"PartOfSpeech": "NNP", "CharacterOffsetBegin": 2601, "CharacterOffsetEnd": 2607}], ["Grossner", {"PartOfSpeech": "NNP", "CharacterOffsetBegin": 2608, "CharacterOffsetEnd": 2616}], ["of", {"PartOfSpeech": "IN", "CharacterOffsetBegin": 2617, "CharacterOffsetEnd": 2619}], ["Toronto-based", {"PartOfSpeech": "JJ", "CharacterOffsetBegin": 2620, "CharacterOffsetEnd": 2633}], ["Richardson", {"PartOfSpeech": "NNP", "CharacterOffsetBegin": 2634, "CharacterOffsetEnd": 2644}], ["Greenshields", {"PartOfSpeech": "NNP", "CharacterOffsetBegin": 2645, "CharacterOffsetEnd": 2657}], ["Inc.", {"PartOfSpeech": "NNP", "CharacterOffsetBegin": 2658, "CharacterOffsetEnd": 2662}], [",", {"PartOfSpeech": ",", "CharacterOffsetBegin": 2662, "CharacterOffsetEnd": 2663}], ["believe", {"PartOfSpeech": "VBP", "CharacterOffsetBegin": 2664, "CharacterOffsetEnd": 2671}], ["the", {"PartOfSpeech": "DT", "CharacterOffsetBegin": 2672, "CharacterOffsetEnd": 2675}], ["government", {"PartOfSpeech": "NN", "CharacterOffsetBegin": 2676, "CharacterOffsetEnd": 2686}], ["ruling", {"PartOfSpeech": "NN", "CharacterOffsetBegin": 2687, "CharacterOffsetEnd": 2693}], ["leaves", {"PartOfSpeech": "VBZ", "CharacterOffsetBegin": 2694, "CharacterOffsetEnd": 2700}], ["the", {"PartOfSpeech": "DT", "CharacterOffsetBegin": 2701, "CharacterOffsetEnd": 2704}], ["door", {"PartOfSpeech": "NN", "CharacterOffsetBegin": 2705, "CharacterOffsetEnd": 2709}], ["open", {"PartOfSpeech": "JJ", "CharacterOffsetBegin": 2710, "CharacterOffsetEnd": 2714}], ["for", {"PartOfSpeech": "IN", "CharacterOffsetBegin": 2715, "CharacterOffsetEnd": 2718}], ["other", {"PartOfSpeech": "JJ", "CharacterOffsetBegin": 2719, "CharacterOffsetEnd": 2724}], ["bidders", {"PartOfSpeech": "NNS", "CharacterOffsetBegin": 2725, "CharacterOffsetEnd": 2732}], [",", {"PartOfSpeech": ",", "CharacterOffsetBegin": 2732, "CharacterOffsetEnd": 2733}], ["such", {"PartOfSpeech": "JJ", "CharacterOffsetBegin": 2734, "CharacterOffsetEnd": 2738}], ["as", {"PartOfSpeech": "IN", "CharacterOffsetBegin": 2739, "CharacterOffsetEnd": 2741}], ["Switzerland", {"PartOfSpeech": "NNP", "CharacterOffsetBegin": 2742, "CharacterOffsetEnd": 2753}], ["'s", {"PartOfSpeech": "POS", "CharacterOffsetBegin": 2753, "CharacterOffsetEnd": 2755}], ["Ciba-Geigy", {"PartOfSpeech": "NNP", "CharacterOffsetBegin": 2756, "CharacterOffsetEnd": 2766}], ["and", {"PartOfSpeech": "CC", "CharacterOffsetBegin": 2767, "CharacterOffsetEnd": 2770}], ["Chiron", {"PartOfSpeech": "NNP", "CharacterOffsetBegin": 2771, "CharacterOffsetEnd": 2777}], ["Corp.", {"PartOfSpeech": "NNP", "CharacterOffsetBegin": 2778, "CharacterOffsetEnd": 2783}], ["of", {"PartOfSpeech": "IN", "CharacterOffsetBegin": 2784, "CharacterOffsetEnd": 2786}], ["Emeryville", {"PartOfSpeech": "NNP", "CharacterOffsetBegin": 2787, "CharacterOffsetEnd": 2797}], [",", {"PartOfSpeech": ",", "CharacterOffsetBegin": 2797, "CharacterOffsetEnd": 2798}], ["Calif.", {"PartOfSpeech": "NNP", "CharacterOffsetBegin": 2799, "CharacterOffsetEnd": 2804}], [".", {"PartOfSpeech": ".", "CharacterOffsetBegin": 2804, "CharacterOffsetEnd": 2805}]]}, {"parsetree": "( (S (NP (NP (NNS Officials)) (PP (IN for) (NP (DT the) (CD two) (NNS concerns))) (, ,) (SBAR (WHNP (WDT which)) (S (VP (VBP are) (VP (VBG bidding) (NP (NP ($ C$) (CD 30)) (NP (DT a) (NN share))) (PP (IN for) (NP (NNP Connaught))))))) (, ,)) (VP (MD could) (RB n't) (VP (VB be) (VP (VBN reached) (PP (IN for) (NP (NN comment)))))) (. .)))", "dependencies": [["root", "ROOT-0", "reached-20"], ["nsubjpass", "reached-20", "Officials-1"], ["case", "concerns-5", "for-2"], ["det", "concerns-5", "the-3"], ["nummod", "concerns-5", "two-4"], ["nmod", "Officials-1", "concerns-5"], ["punct", "Officials-1", ",-6"], ["nsubj", "bidding-9", "which-7"], ["aux", "bidding-9", "are-8"], ["acl:relcl", "Officials-1", "bidding-9"], ["dep", "30-11", "C$-10"], ["dobj", "bidding-9", "30-11"], ["det", "share-13", "a-12"], ["dep", "30-11", "share-13"], ["case", "Connaught-15", "for-14"], ["nmod", "bidding-9", "Connaught-15"], ["punct", "Officials-1", ",-16"], ["aux", "reached-20", "could-17"], ["neg", "reached-20", "n't-18"], ["auxpass", "reached-20", "be-19"], ["case", "comment-22", "for-21"], ["nmod", "reached-20", "comment-22"], ["punct", "reached-20", ".-23"]], "words": [["Officials", {"PartOfSpeech": "NNS", "CharacterOffsetBegin": 2806, "CharacterOffsetEnd": 2815}], ["for", {"PartOfSpeech": "IN", "CharacterOffsetBegin": 2816, "CharacterOffsetEnd": 2819}], ["the", {"PartOfSpeech": "DT", "CharacterOffsetBegin": 2820, "CharacterOffsetEnd": 2823}], ["two", {"PartOfSpeech": "CD", "CharacterOffsetBegin": 2824, "CharacterOffsetEnd": 2827}], ["concerns", {"PartOfSpeech": "NNS", "CharacterOffsetBegin": 2828, "CharacterOffsetEnd": 2836}], [",", {"PartOfSpeech": ",", "CharacterOffsetBegin": 2836, "CharacterOffsetEnd": 2837}], ["which", {"PartOfSpeech": "WDT", "CharacterOffsetBegin": 2838, "CharacterOffsetEnd": 2843}], ["are", {"PartOfSpeech": "VBP", "CharacterOffsetBegin": 2844, "CharacterOffsetEnd": 2847}], ["bidding", {"PartOfSpeech": "VBG", "CharacterOffsetBegin": 2848, "CharacterOffsetEnd": 2855}], ["C$", {"PartOfSpeech": "$", "CharacterOffsetBegin": 2856, "CharacterOffsetEnd": 2858}], ["30", {"PartOfSpeech": "CD", "CharacterOffsetBegin": 2858, "CharacterOffsetEnd": 2860}], ["a", {"PartOfSpeech": "DT", "CharacterOffsetBegin": 2861, "CharacterOffsetEnd": 2862}], ["share", {"PartOfSpeech": "NN", "CharacterOffsetBegin": 2863, "CharacterOffsetEnd": 2868}], ["for", {"PartOfSpeech": "IN", "CharacterOffsetBegin": 2869, "CharacterOffsetEnd": 2872}], ["Connaught", {"PartOfSpeech": "NNP", "CharacterOffsetBegin": 2873, "CharacterOffsetEnd": 2882}], [",", {"PartOfSpeech": ",", "CharacterOffsetBegin": 2882, "CharacterOffsetEnd": 2883}], ["could", {"PartOfSpeech": "MD", "CharacterOffsetBegin": 2884, "CharacterOffsetEnd": 2889}], ["n't", {"PartOfSpeech": "RB", "CharacterOffsetBegin": 2889, "CharacterOffsetEnd": 2892}], ["be", {"PartOfSpeech": "VB", "CharacterOffsetBegin": 2893, "CharacterOffsetEnd": 2895}], ["reached", {"PartOfSpeech": "VBN", "CharacterOffsetBegin": 2896, "CharacterOffsetEnd": 2903}], ["for", {"PartOfSpeech": "IN", "CharacterOffsetBegin": 2904, "CharacterOffsetEnd": 2907}], ["comment", {"PartOfSpeech": "NN", "CharacterOffsetBegin": 2908, "CharacterOffsetEnd": 2915}], [".", {"PartOfSpeech": ".", "CharacterOffsetBegin": 2915, "CharacterOffsetEnd": 2916}]]}, {"parsetree": "( (S (NP (ADJP (JJ French) (JJ state-owned)) (NNP Rhone-Poulenc) (NNP S.A.)) (VP (VBZ holds) (NP (NP (CD 51) (NN %)) (PP (IN of) (NP (NNP Merieux))))) (. .)))", "dependencies": [["root", "ROOT-0", "holds-5"], ["amod", "state-owned-2", "French-1"], ["amod", "S.A.-4", "state-owned-2"], ["compound", "S.A.-4", "Rhone-Poulenc-3"], ["nsubj", "holds-5", "S.A.-4"], ["nummod", "%-7", "51-6"], ["dobj", "holds-5", "%-7"], ["case", "Merieux-9", "of-8"], ["nmod", "%-7", "Merieux-9"], ["punct", "holds-5", ".-10"]], "words": [["French", {"PartOfSpeech": "JJ", "CharacterOffsetBegin": 2919, "CharacterOffsetEnd": 2925}], ["state-owned", {"PartOfSpeech": "JJ", "CharacterOffsetBegin": 2926, "CharacterOffsetEnd": 2937}], ["Rhone-Poulenc", {"PartOfSpeech": "NNP", "CharacterOffsetBegin": 2938, "CharacterOffsetEnd": 2951}], ["S.A.", {"PartOfSpeech": "NNP", "CharacterOffsetBegin": 2952, "CharacterOffsetEnd": 2956}], ["holds", {"PartOfSpeech": "VBZ", "CharacterOffsetBegin": 2957, "CharacterOffsetEnd": 2962}], ["51", {"PartOfSpeech": "CD", "CharacterOffsetBegin": 2963, "CharacterOffsetEnd": 2965}], ["%", {"PartOfSpeech": "NN", "CharacterOffsetBegin": 2965, "CharacterOffsetEnd": 2966}], ["of", {"PartOfSpeech": "IN", "CharacterOffsetBegin": 2967, "CharacterOffsetEnd": 2969}], ["Merieux", {"PartOfSpeech": "NNP", "CharacterOffsetBegin": 2970, "CharacterOffsetEnd": 2977}], [".", {"PartOfSpeech": ".", "CharacterOffsetBegin": 2977, "CharacterOffsetEnd": 2978}]]}]}}