{"wsj_2338": [{"Connective": {"TokenList": [37], "raw": ["as"], "CharacterOffset": ["201..203"]}, "Arg1": {"TokenList": [23, 24, 25, 26, 27, 28, 29, 30, 31, 32, 33, 34, 35, 36], "raw": ["that", "as", "many", "as", "five", "North", "American", "assembly", "plants", "may", "not", "survive", "the", "mid-1990s"], "CharacterOffset": ["119..123", "124..126", "127..131", "132..134", "135..139", "140..145", "146..154", "155..163", "164..170", "171..174", "175..178", "179..186", "187..190", "191..200"]}, "Arg2": {"TokenList": [38, 39, 40, 41, 42, 43, 44, 45, 46], "raw": ["the", "corporation", "struggles", "to", "cut", "its", "excess", "vehicle-making", "capacity"], "CharacterOffset": ["204..207", "208..219", "220..229", "230..232", "233..236", "237..240", "241..247", "248..262", "263..271"]}}, {"Connective": {"TokenList": [263], "raw": ["before"], "CharacterOffset": ["1425..1431"]}, "Arg1": {"TokenList": [252, 253, 254, 255, 256, 257, 258, 259, 260, 261, 262], "raw": ["their", "strategy", "to", "reduce", "capacity", "and", "the", "work", "force", "in", "place"], "CharacterOffset": ["1363..1368", "1369..1377", "1378..1380", "1381..1387", "1388..1396", "1397..1400", "1401..1404", "1405..1409", "1410..1415", "1416..1418", "1419..1424"]}, "Arg2": {"TokenList": [264, 265, 266], "raw": ["those", "talks", "begin"], "CharacterOffset": ["1432..1437", "1438..1443", "1444..1449"]}}, {"Connective": {"TokenList": [692], "raw": ["and"], "CharacterOffset": ["3760..3763"]}, "Arg1": {"TokenList": [683, 684, 685, 686, 687, 688, 689, 690], "raw": ["the", "plant", "has", "no", "new", "product", "lined", "up"], "CharacterOffset": ["3721..3724", "3725..3730", "3731..3734", "3735..3737", "3738..3741", "3742..3749", "3750..3755", "3756..3758"]}, "Arg2": {"TokenList": [694, 695, 696, 697], "raw": ["none", "of", "us", "knows"], "CharacterOffset": ["3765..3769", "3770..3772", "3773..3775", "3776..3781"]}}, {"Connective": {"TokenList": [699], "raw": ["when"], "CharacterOffset": ["3783..3787"]}, "Arg1": {"TokenList": [656, 657, 658, 659, 660, 661, 662, 663, 664, 665, 666, 667, 668, 669, 670, 671, 672, 673, 674, 675, 676, 677, 678, 679, 680, 681, 682], "raw": ["At", "the", "Oklahoma", "City", "plant", ",", "which", "employs", "about", "6,000", "workers", "building", "the", "eight-year-old", "A-body", "mid-sized", "cars", ",", "Steve", "Featherston", ",", "UAW", "local", "vice", "president", ",", "said"], "CharacterOffset": ["3558..3560", "3561..3564", "3565..3573", "3574..3578", "3579..3584", "3584..3585", "3586..3591", "3592..3599", "3600..3605", "3606..3611", "3612..3619", "3620..3628", "3629..3632", "3633..3647", "3648..3654", "3655..3664", "3665..3669", "3669..3670", "3671..3676", "3677..3688", "3688..3689", "3690..3693", "3694..3699", "3700..3704", "3705..3714", "3714..3715", "3716..3720"]}, "Arg2": {"TokenList": [700, 701, 702, 703, 704], "raw": ["the", "A-body", "cars", "will", "die"], "CharacterOffset": ["3788..3791", "3792..3798", "3799..3803", "3804..3808", "3809..3812"]}}, {"Connective": {"TokenList": [767], "raw": ["before"], "CharacterOffset": ["4171..4177"]}, "Arg1": {"TokenList": [754, 755, 756, 757, 758, 759, 760, 761, 762, 763, 764, 765, 766], "raw": ["The", "Fiero", "plant", "was", "viewed", "as", "a", "model", "of", "union-management", "cooperation", "at", "GM"], "CharacterOffset": ["4095..4098", "4099..4104", "4105..4110", "4111..4114", "4115..4121", "4122..4124", "4125..4126", "4127..4132", "4133..4135", "4136..4152", "4153..4164", "4165..4167", "4168..4170"]}, "Arg2": {"TokenList": [768, 769, 770, 771, 772, 773, 774, 775, 776, 777, 778, 779, 780, 781], "raw": ["slow", "sales", "of", "the", "Fiero", "forced", "the", "company", "to", "close", "the", "factory", "last", "year"], "CharacterOffset": ["4178..4182", "4183..4188", "4189..4191", "4192..4195", "4196..4201", "4202..4208", "4209..4212", "4213..4220", "4221..4223", "4224..4229", "4230..4233", "4234..4241", "4242..4246", "4247..4251"]}}, {"Connective": {"TokenList": [790, 791, 792], "raw": ["as", "a", "result"], "CharacterOffset": ["4302..4304", "4305..4306", "4307..4313"]}, "Arg1": {"TokenList": [785], "raw": ["have"], "CharacterOffset": ["4269..4273"]}, "Arg2": {"TokenList": [787, 788, 789], "raw": ["a", "beating", "politically"], "CharacterOffset": ["4280..4281", "4282..4289", "4290..4301"]}}, {"Connective": {"TokenList": [271], "raw": ["however"], "CharacterOffset": ["1466..1473"]}, "Arg1": {"TokenList": [247, 248, 249, 250, 251, 252, 253, 254, 255, 256, 257, 258, 259, 260, 261, 262, 263, 264, 265, 266], "raw": ["GM", "officials", "want", "to", "get", "their", "strategy", "to", "reduce", "capacity", "and", "the", "work", "force", "in", "place", "before", "those", "talks", "begin"], "CharacterOffset": ["1338..1340", "1341..1350", "1351..1355", "1356..1358", "1359..1362", "1363..1368", "1369..1377", "1378..1380", "1381..1387", "1388..1396", "1397..1400", "1401..1404", "1405..1409", "1410..1415", "1416..1418", "1419..1424", "1425..1431", "1432..1437", "1438..1443", "1444..1449"]}, "Arg2": {"TokenList": [268, 269, 273, 274, 275, 276, 277, 278, 279, 280, 281, 282, 283, 284, 285, 286, 287, 288, 289, 290, 291, 292, 293, 294, 295, 296, 297, 298, 299, 300, 301, 302, 303], "raw": ["The", "problem", "is", "that", "GM", "'s", "moves", "are", "coming", "at", "a", "time", "when", "UAW", "leaders", "are", "trying", "to", "silence", "dissidents", "who", "charge", "the", "union", "is", "too", "passive", "in", "the", "face", "of", "GM", "layoffs"], "CharacterOffset": ["1453..1456", "1457..1464", "1475..1477", "1478..1482", "1483..1485", "1485..1487", "1488..1493", "1494..1497", "1498..1504", "1505..1507", "1508..1509", "1510..1514", "1515..1519", "1520..1523", "1524..1531", "1532..1535", "1536..1542", "1543..1545", "1546..1553", "1554..1564", "1565..1568", "1569..1575", "1576..1579", "1580..1585", "1586..1588", "1589..1592", "1593..1600", "1601..1603", "1604..1607", "1608..1612", "1613..1615", "1616..1618", "1619..1626"]}}, {"Connective": {"TokenList": [490], "raw": ["But"], "CharacterOffset": ["2669..2672"]}, "Arg1": {"TokenList": [460, 461, 462, 463, 464, 465, 466, 467, 468, 469, 470, 471, 472, 473, 474, 475, 476, 477, 478, 479, 480, 481, 482, 483, 484, 485, 486, 487, 488], "raw": ["Robert", "White", ",", "Canadian", "Auto", "Workers", "union", "president", ",", "used", "the", "impending", "Scarborough", "shutdown", "to", "criticize", "the", "U.S.-Canada", "free", "trade", "agreement", "and", "its", "champion", ",", "Prime", "Minister", "Brian", "Mulroney"], "CharacterOffset": ["2475..2481", "2482..2487", "2487..2488", "2489..2497", "2498..2502", "2503..2510", "2511..2516", "2517..2526", "2526..2527", "2528..2532", "2533..2536", "2537..2546", "2547..2558", "2559..2567", "2568..2570", "2571..2580", "2581..2584", "2585..2596", "2597..2601", "2602..2607", "2608..2617", "2618..2621", "2622..2625", "2626..2634", "2634..2635", "2636..2641", "2642..2650", "2651..2656", "2657..2665"]}, "Arg2": {"TokenList": [491, 492, 493, 494, 495, 496, 497, 498, 499, 500, 501, 502, 503, 504, 505, 506, 507, 508, 509, 510], "raw": ["Canadian", "auto", "workers", "may", "benefit", "from", "a", "separate", "GM", "move", "that", "affects", "three", "U.S.", "car", "plants", "and", "one", "in", "Quebec"], "CharacterOffset": ["2673..2681", "2682..2686", "2687..2694", "2695..2698", "2699..2706", "2707..2711", "2712..2713", "2714..2722", "2723..2725", "2726..2730", "2731..2735", "2736..2743", "2744..2749", "2750..2754", "2755..2758", "2759..2765", "2766..2769", "2770..2773", "2774..2776", "2777..2783"]}}, {"Connective": {"TokenList": [725], "raw": ["however"], "CharacterOffset": ["3910..3917"]}, "Arg1": {"TokenList": [708, 709, 710, 711, 712, 713, 714, 715, 716, 717, 718, 719, 720], "raw": ["he", "believes", "GM", "has", "plans", "to", "keep", "building", "A-body", "cars", "into", "the", "mid-1990s"], "CharacterOffset": ["3822..3824", "3825..3833", "3834..3836", "3837..3840", "3841..3846", "3847..3849", "3850..3854", "3855..3863", "3864..3870", "3871..3875", "3876..3880", "3881..3884", "3885..3894"]}, "Arg2": {"TokenList": [722, 723, 727, 728, 729, 730, 731, 732, 733, 734, 735, 736, 737, 738, 739, 740, 741, 742, 743, 744, 745, 746, 747, 748, 749, 750, 751, 752], "raw": ["At", "Pontiac", "the", "Camaro-Firebird", "decision", "appears", "to", "erase", "UAW", "hopes", "that", "GM", "would", "reopen", "the", "shuttered", "assembly", "plant", "that", "last", "built", "the", "plastic-bodied", ",", "two-seater", "Pontiac", "Fiero", "model"], "CharacterOffset": ["3898..3900", "3901..3908", "3919..3922", "3923..3938", "3939..3947", "3948..3955", "3956..3958", "3959..3964", "3965..3968", "3969..3974", "3975..3979", "3980..3982", "3983..3988", "3989..3995", "3996..3999", "4000..4009", "4010..4018", "4019..4024", "4025..4029", "4030..4034", "4035..4040", "4041..4044", "4045..4059", "4059..4060", "4061..4071", "4072..4079", "4080..4085", "4086..4091"]}}]}